<?xml version="1.0" encoding="UTF-8"?>
<ticket>
  <assigned-user-id type="integer" nil="true"></assigned-user-id>
  <attachments-count type="integer">0</attachments-count>
  <closed type="boolean">true</closed>
  <created-at type="datetime">2011-03-29T02:29:22+01:00</created-at>
  <creator-id type="integer">29265</creator-id>
  <milestone-due-on type="datetime" nil="true"></milestone-due-on>
  <milestone-id type="integer">9903</milestone-id>
  <number type="integer">2025</number>
  <permalink>add-a-check-for-reserved-words-in-generators</permalink>
  <priority type="integer">0</priority>
  <project-id type="integer">8994</project-id>
  <raw-data type="binary" nil="true" encoding="base64"></raw-data>
  <state>invalid</state>
  <tag nil="true"></tag>
  <title>add a check for reserved words in generators</title>
  <updated-at type="datetime">2011-03-29T02:29:22+01:00</updated-at>
  <user-id type="integer">19965</user-id>
  <version type="integer">6</version>
  <user-name>Jos&#233; Valim</user-name>
  <creator-name>kirillrdy</creator-name>
  <url>http://rails.lighthouseapp.com/projects/8994/tickets/2025</url>
  <milestone-title>2.x</milestone-title>
  <priority-name nil="true"></priority-name>
  <original-body>It would be very useful and save developers a lot of time, if you check for reserved keywords in generators like scaffold etc.

example
./script/generate scaffold action name:string

Action is Rails reserved keyword, and posting to /actions/create will fail.

list of keywords
http://wiki.rubyonrails.org/rails/pages/ReservedWords

Thank you</original-body>
  <latest-body>It would be very useful and save developers a lot of time, if you check for reserved keywords in generators like scaffold etc.

example
./script/generate scaffold action name:string

Action is Rails reserved keyword, and posting to /actions/create will fail.

list of keywords
http://wiki.rubyonrails.org/rails/pages/ReservedWords

Thank you</latest-body>
  <original-body-html>&lt;div&gt;&lt;p&gt;It would be very useful and save developers a lot of time, if
you check for reserved keywords in generators like scaffold
etc.&lt;/p&gt;
&lt;p&gt;example ./script/generate scaffold action name:string&lt;/p&gt;
&lt;p&gt;Action is Rails reserved keyword, and posting to /actions/create
will fail.&lt;/p&gt;
&lt;p&gt;list of keywords &lt;a href=&quot;http://wiki.rubyonrails.org/rails/pages/ReservedWords&quot;&gt;http://wiki.rubyonrails.org/rail...&lt;/a&gt;&lt;/p&gt;
&lt;p&gt;Thank you&lt;/p&gt;&lt;/div&gt;</original-body-html>
  <versions type="array">
    <version type="Ticket::Version">
      <assigned-user-id type="integer" nil="true"></assigned-user-id>
      <attachments-count type="integer">0</attachments-count>
      <body>It would be very useful and save developers a lot of time, if you check for reserved keywords in generators like scaffold etc.

example
./script/generate scaffold action name:string

Action is Rails reserved keyword, and posting to /actions/create will fail.

list of keywords
http://wiki.rubyonrails.org/rails/pages/ReservedWords

Thank you</body>
      <body-html>&lt;div&gt;&lt;p&gt;It would be very useful and save developers a lot of time, if
you check for reserved keywords in generators like scaffold
etc.&lt;/p&gt;
&lt;p&gt;example ./script/generate scaffold action name:string&lt;/p&gt;
&lt;p&gt;Action is Rails reserved keyword, and posting to /actions/create
will fail.&lt;/p&gt;
&lt;p&gt;list of keywords &lt;a href=&quot;http://wiki.rubyonrails.org/rails/pages/ReservedWords&quot;&gt;http://wiki.rubyonrails.org/rail...&lt;/a&gt;&lt;/p&gt;
&lt;p&gt;Thank you&lt;/p&gt;&lt;/div&gt;</body-html>
      <closed type="boolean">false</closed>
      <created-at type="datetime">2009-02-20T00:14:43+00:00</created-at>
      <creator-id type="integer">29265</creator-id>
      <diffable-attributes type="yaml">--- {}

</diffable-attributes>
      <milestone-id type="integer">9903</milestone-id>
      <number type="integer">2025</number>
      <permalink>add-a-check-for-reserved-words-in-generators</permalink>
      <priority type="integer">0</priority>
      <project-id type="integer">8994</project-id>
      <state>new</state>
      <tag nil="true"></tag>
      <title>add a check for reserved words in generators</title>
      <updated-at type="datetime">2009-02-20T00:14:47+00:00</updated-at>
      <user-id type="integer">29265</user-id>
      <version type="integer">1</version>
      <user-name>kirillrdy</user-name>
      <creator-name>kirillrdy</creator-name>
      <url>http://rails.lighthouseapp.com/projects/8994/tickets/2025</url>
      <milestone-title>2.x</milestone-title>
      <priority-name nil="true"></priority-name>
    </version>
    <version type="Ticket::Version">
      <assigned-user-id type="integer" nil="true"></assigned-user-id>
      <attachments-count type="integer">0</attachments-count>
      <body>If you're motivated to do this, please send along a patch. But note that in Rails 3.0, the plan is to make the generators able to handle various combinations of ORM/Testing Library/Javascript library (at least), so the issue of figuring out what the reserved words are becomes practically impossible.</body>
      <body-html>&lt;div&gt;&lt;p&gt;If you're motivated to do this, please send along a patch. But
note that in Rails 3.0, the plan is to make the generators able to
handle various combinations of ORM/Testing Library/Javascript
library (at least), so the issue of figuring out what the reserved
words are becomes practically impossible.&lt;/p&gt;&lt;/div&gt;</body-html>
      <closed type="boolean">true</closed>
      <created-at type="datetime">2009-04-22T22:12:10+01:00</created-at>
      <creator-id type="integer">29265</creator-id>
      <diffable-attributes type="yaml">--- 
:state: new
</diffable-attributes>
      <milestone-id type="integer">9903</milestone-id>
      <number type="integer">2025</number>
      <permalink>add-a-check-for-reserved-words-in-generators</permalink>
      <priority type="integer">0</priority>
      <project-id type="integer">8994</project-id>
      <state>incomplete</state>
      <tag nil="true"></tag>
      <title>add a check for reserved words in generators</title>
      <updated-at type="datetime">2009-04-22T22:12:12+01:00</updated-at>
      <user-id type="integer">7211</user-id>
      <version type="integer">2</version>
      <user-name>CancelProfileIsBroken</user-name>
      <creator-name>kirillrdy</creator-name>
      <url>http://rails.lighthouseapp.com/projects/8994/tickets/2025</url>
      <milestone-title>2.x</milestone-title>
      <priority-name nil="true"></priority-name>
    </version>
    <version type="Ticket::Version">
      <assigned-user-id type="integer" nil="true"></assigned-user-id>
      <attachments-count type="integer">0</attachments-count>
      <body>Hi, I am willing to implement it myself.

I know full protection will be hard to implement,
but lets start with something simple, like Model names and properties (database fields)

I foolishly created(scaffolded) a model with string property &quot;action&quot; on it.
It was really hard to find why &quot;update&quot; didn't work.
it was posting My model's hash :action =&gt; {fields}, and overwrote rail's params[:action].

Wasn't easy to find.(no helpful error message or anything)

For first, at least have a blacklist of Model names (eg File) and fields (eg Action).

I haven't been following rails 3.0 development. But I will try to put some time into this soon.

Thanks,

Kirill R</body>
      <body-html>&lt;div&gt;&lt;p&gt;Hi, I am willing to implement it myself.&lt;/p&gt;
&lt;p&gt;I know full protection will be hard to implement, but lets start
with something simple, like Model names and properties (database
fields)&lt;/p&gt;
&lt;p&gt;I foolishly created(scaffolded) a model with string property
&quot;action&quot; on it. It was really hard to find why &quot;update&quot; didn't
work. it was posting My model's hash :action =&amp;gt; {fields}, and
overwrote rail's params[:action].&lt;/p&gt;
&lt;p&gt;Wasn't easy to find.(no helpful error message or anything)&lt;/p&gt;
&lt;p&gt;For first, at least have a blacklist of Model names (eg File)
and fields (eg Action).&lt;/p&gt;
&lt;p&gt;I haven't been following rails 3.0 development. But I will try
to put some time into this soon.&lt;/p&gt;
&lt;p&gt;Thanks,&lt;/p&gt;
&lt;p&gt;Kirill R&lt;/p&gt;&lt;/div&gt;</body-html>
      <closed type="boolean">true</closed>
      <created-at type="datetime">2009-04-22T22:55:37+01:00</created-at>
      <creator-id type="integer">29265</creator-id>
      <diffable-attributes type="yaml">--- {}

</diffable-attributes>
      <milestone-id type="integer">9903</milestone-id>
      <number type="integer">2025</number>
      <permalink>add-a-check-for-reserved-words-in-generators</permalink>
      <priority type="integer">0</priority>
      <project-id type="integer">8994</project-id>
      <state>incomplete</state>
      <tag nil="true"></tag>
      <title>add a check for reserved words in generators</title>
      <updated-at type="datetime">2009-04-22T22:55:38+01:00</updated-at>
      <user-id type="integer">29265</user-id>
      <version type="integer">3</version>
      <user-name>kirillrdy</user-name>
      <creator-name>kirillrdy</creator-name>
      <url>http://rails.lighthouseapp.com/projects/8994/tickets/2025</url>
      <milestone-title>2.x</milestone-title>
      <priority-name nil="true"></priority-name>
    </version>
    <version type="Ticket::Version">
      <assigned-user-id type="integer" nil="true"></assigned-user-id>
      <attachments-count type="integer">0</attachments-count>
      <body>He already check for class collisions in both Rails 2.3 stable and master. For instance, you cannot create a model named File.

I cannot reproduce the update behavior, because the model action is available at params[:model][:action] and not params[:action]. A couple of keywords are already checked on migrations too.</body>
      <body-html>&lt;div&gt;&lt;p&gt;He already check for class collisions in both Rails 2.3 stable
and master. For instance, you cannot create a model named File.&lt;/p&gt;
&lt;p&gt;I cannot reproduce the update behavior, because the model action
is available at params[:model][:action] and not params[:action]. A
couple of keywords are already checked on migrations too.&lt;/p&gt;&lt;/div&gt;</body-html>
      <closed type="boolean">true</closed>
      <created-at type="datetime">2009-08-10T11:16:26+01:00</created-at>
      <creator-id type="integer">29265</creator-id>
      <diffable-attributes type="yaml">--- 
:state: incomplete
</diffable-attributes>
      <milestone-id type="integer">9903</milestone-id>
      <number type="integer">2025</number>
      <permalink>add-a-check-for-reserved-words-in-generators</permalink>
      <priority type="integer">0</priority>
      <project-id type="integer">8994</project-id>
      <state>invalid</state>
      <tag nil="true"></tag>
      <title>add a check for reserved words in generators</title>
      <updated-at type="datetime">2009-08-10T11:16:28+01:00</updated-at>
      <user-id type="integer">19965</user-id>
      <version type="integer">4</version>
      <user-name>Jos&#233; Valim</user-name>
      <creator-name>kirillrdy</creator-name>
      <url>http://rails.lighthouseapp.com/projects/8994/tickets/2025</url>
      <milestone-title>2.x</milestone-title>
      <priority-name nil="true"></priority-name>
    </version>
    <version type="Ticket::Version">
      <assigned-user-id type="integer" nil="true"></assigned-user-id>
      <attachments-count type="integer">0</attachments-count>
      <body>&gt; He already check for class collisions in both Rails 2.3 stable and master. 
&gt; For instance, you cannot create a model named File.

I failed to quickly find the code which does that, could you please find a link?</body>
      <body-html>&lt;div&gt;&lt;blockquote&gt;
&lt;p&gt;He already check for class collisions in both Rails 2.3 stable
and master. For instance, you cannot create a model named File.&lt;/p&gt;
&lt;/blockquote&gt;
&lt;p&gt;I failed to quickly find the code which does that, could you
please find a link?&lt;/p&gt;&lt;/div&gt;</body-html>
      <closed type="boolean">true</closed>
      <created-at type="datetime">2009-08-19T13:36:33+01:00</created-at>
      <creator-id type="integer">29265</creator-id>
      <diffable-attributes type="yaml">--- {}

</diffable-attributes>
      <milestone-id type="integer">9903</milestone-id>
      <number type="integer">2025</number>
      <permalink>add-a-check-for-reserved-words-in-generators</permalink>
      <priority type="integer">0</priority>
      <project-id type="integer">8994</project-id>
      <state>invalid</state>
      <tag nil="true"></tag>
      <title>add a check for reserved words in generators</title>
      <updated-at type="datetime">2009-08-19T13:36:36+01:00</updated-at>
      <user-id type="integer">43210</user-id>
      <version type="integer">5</version>
      <user-name>Evgeniy Dolzhenko</user-name>
      <creator-name>kirillrdy</creator-name>
      <url>http://rails.lighthouseapp.com/projects/8994/tickets/2025</url>
      <milestone-title>2.x</milestone-title>
      <priority-name nil="true"></priority-name>
    </version>
    <version type="Ticket::Version">
      <assigned-user-id type="integer" nil="true"></assigned-user-id>
      <attachments-count type="integer">0</attachments-count>
      <body>On master:

http://github.com/rails/rails/blob/ef935240582ef6a7d47a9716e8269db817c91503/railties/lib/generators/base.rb#L174</body>
      <body-html>&lt;div&gt;&lt;p&gt;On master:&lt;/p&gt;
&lt;p&gt;&lt;a href=
&quot;http://github.com/rails/rails/blob/ef935240582ef6a7d47a9716e8269db817c91503/railties/lib/generators/base.rb#L174&quot;&gt;
http://github.com/rails/rails/blob/ef935240582ef6a7d47a9716e8269db8...&lt;/a&gt;&lt;/p&gt;&lt;/div&gt;</body-html>
      <closed type="boolean">true</closed>
      <created-at type="datetime">2009-08-19T13:54:35+01:00</created-at>
      <creator-id type="integer">29265</creator-id>
      <diffable-attributes type="yaml">--- {}

</diffable-attributes>
      <milestone-id type="integer">9903</milestone-id>
      <number type="integer">2025</number>
      <permalink>add-a-check-for-reserved-words-in-generators</permalink>
      <priority type="integer">0</priority>
      <project-id type="integer">8994</project-id>
      <state>invalid</state>
      <tag nil="true"></tag>
      <title>add a check for reserved words in generators</title>
      <updated-at type="datetime">2009-08-19T13:54:41+01:00</updated-at>
      <user-id type="integer">19965</user-id>
      <version type="integer">6</version>
      <user-name>Jos&#233; Valim</user-name>
      <creator-name>kirillrdy</creator-name>
      <url>http://rails.lighthouseapp.com/projects/8994/tickets/2025</url>
      <milestone-title>2.x</milestone-title>
      <priority-name nil="true"></priority-name>
    </version>
    <version type="Ticket::Version">
      <assigned-user-id type="integer" nil="true"></assigned-user-id>
      <attachments-count type="integer">0</attachments-count>
      <body>It is known that &lt;a href=&quot;http://www.nikedunks2011.com/&quot;&gt;Nike shoes&lt;/a&gt; are popular and famous. Many people become fans of &lt;a href=&quot;http://www.nikedunks2011.com/&quot;&gt;cheap nike shoes&lt;/a&gt;. Nike has a wide array of products such as designer &lt;a href=&quot;http://www.nikedunks2011.com/nike-dunks-c-155.html&quot;&gt;dunks shoes&lt;/a&gt;, Nike clothing, Nike and accessories. Like Nike Air &lt;a href=&quot;http://www.nikedunks2011.com/nike-dunks-nike-dunk-high-c-155_212.html&quot;&gt;nike dunk high&lt;/a&gt;, Kobe Bryant, shoes, all the classic style of the &lt;a href=&quot;http://www.nikedunks2011.com/nike-air-max-c-215.html&quot;&gt;nike air max&lt;/a&gt;.Cheap Nike Air Max sustained release the latest model of the product on site is a series of free &lt;a href=&quot;http://www.nikedunks2011.com/nike-air-max-nike-air-max-90-c-215_220.html&quot;&gt;air max 90&lt;/a&gt; Air Max shoes.Nike, we now have our own in a typical run a series of &lt;a href=&quot;http://www.nikedunks2011.com/nike-basketball-shoes-c-235.html&quot;&gt;basketball shoes&lt;/a&gt;.Women&#8217;s Slipper&#160;You ll fall color &#8216; in love with them at first sight.It is a shoe that is comfortable and has lightweight.It damping, high performance, fit and style that is needed for people run.The Discount &lt;a href=&quot;http://www.nikedunks2011.com/nike-basketball-shoes-nike-lebron-james-c-235_242.html&quot;&gt;lebron james shoes&lt;/a&gt; 2009 has proved extremely shoe does it all and stylish.This more.We have fashionable &lt;a href=&quot;http://www.nikedunks2011.com/nike-air-jordan-c-17.html&quot;&gt;sair jordan 2011&lt;/a&gt; outlet that will go well with any of you buy clothes.Our hot styles are cheap &lt;a href=&quot;http://www.nikedunks2011.com/nike-air-force-1-c-18.html&quot;&gt;nike force one&lt;/a&gt;, and cheap Air Max 90, &lt;a href=&quot;http://www.nikedunks2011.com/nike-air-griffey-max-c-213.html&quot;&gt;Nike Air Griffey Max&lt;/a&gt; 360 and flights for the styles on.all comfortable and suitable for both sportswear and casual clothing.</body>
      <body-html>&lt;div&gt;&lt;p&gt;It is known that &lt;a href=&quot;http://www.nikedunks2011.com/&quot;&gt;Nike
shoes&lt;/a&gt; are popular and famous. Many people become fans of
&lt;a href=&quot;http://www.nikedunks2011.com/&quot;&gt;cheap nike shoes&lt;/a&gt;. Nike
has a wide array of products such as designer &lt;a href=
&quot;http://www.nikedunks2011.com/nike-dunks-c-155.html&quot;&gt;dunks
shoes&lt;/a&gt;, Nike clothing, Nike and accessories. Like Nike Air
&lt;a href=
&quot;http://www.nikedunks2011.com/nike-dunks-nike-dunk-high-c-155_212.html&quot;&gt;
nike dunk high&lt;/a&gt;, Kobe Bryant, shoes, all the classic style of
the &lt;a href=
&quot;http://www.nikedunks2011.com/nike-air-max-c-215.html&quot;&gt;nike air
max&lt;/a&gt;.Cheap Nike Air Max sustained release the latest model of
the product on site is a series of free &lt;a href=
&quot;http://www.nikedunks2011.com/nike-air-max-nike-air-max-90-c-215_220.html&quot;&gt;
air max 90&lt;/a&gt; Air Max shoes.Nike, we now have our own in a typical
run a series of &lt;a href=
&quot;http://www.nikedunks2011.com/nike-basketball-shoes-c-235.html&quot;&gt;basketball
shoes&lt;/a&gt;.Women&amp;#8217;s Slipper&amp;nbsp;You ll fall color &amp;#8216; in
love with them at first sight.It is a shoe that is comfortable and
has lightweight.It damping, high performance, fit and style that is
needed for people run.The Discount &lt;a href=
&quot;http://www.nikedunks2011.com/nike-basketball-shoes-nike-lebron-james-c-235_242.html&quot;&gt;
lebron james shoes&lt;/a&gt; 2009 has proved extremely shoe does it all
and stylish.This more.We have fashionable &lt;a href=
&quot;http://www.nikedunks2011.com/nike-air-jordan-c-17.html&quot;&gt;sair
jordan 2011&lt;/a&gt; outlet that will go well with any of you buy
clothes.Our hot styles are cheap &lt;a href=
&quot;http://www.nikedunks2011.com/nike-air-force-1-c-18.html&quot;&gt;nike
force one&lt;/a&gt;, and cheap Air Max 90, &lt;a href=
&quot;http://www.nikedunks2011.com/nike-air-griffey-max-c-213.html&quot;&gt;Nike
Air Griffey Max&lt;/a&gt; 360 and flights for the styles on.all
comfortable and suitable for both sportswear and casual
clothing.&lt;/p&gt;&lt;/div&gt;</body-html>
      <closed type="boolean">true</closed>
      <created-at type="datetime">2010-12-13T10:06:16+00:00</created-at>
      <creator-id type="integer">29265</creator-id>
      <diffable-attributes type="yaml">--- 
:priority: 0
</diffable-attributes>
      <milestone-id type="integer">9903</milestone-id>
      <number type="integer">2025</number>
      <permalink>add-a-check-for-reserved-words-in-generators</permalink>
      <priority type="integer">1265</priority>
      <project-id type="integer">8994</project-id>
      <state>invalid</state>
      <tag nil="true"></tag>
      <title>add a check for reserved words in generators</title>
      <updated-at type="datetime">2010-12-13T13:08:30+00:00</updated-at>
      <user-id type="integer">128794</user-id>
      <version type="integer">7</version>
      <user-name>nike dunks</user-name>
      <creator-name>kirillrdy</creator-name>
      <url>http://rails.lighthouseapp.com/projects/8994/tickets/2025</url>
      <milestone-title>2.x</milestone-title>
      <priority-name nil="true"></priority-name>
    </version>
    <version type="Ticket::Version">
      <assigned-user-id type="integer" nil="true"></assigned-user-id>
      <attachments-count type="integer">0</attachments-count>
      <body>&lt;a href=&quot;http://www.hdvideoconverter-mac.com&quot;&gt;Video Converter for Mac&lt;/a&gt;
&lt;a href=&quot;http://www.hdvideoconverter-mac.com/dvd-converter-for-mac.html&quot;&gt;DVD Converter for Mac&lt;/a&gt; 
&lt;a href=&quot;http://www.hdvideoconverter-mac.com/blu-ray-ripper-for-mac.html&quot;&gt;Blu-Ray Ripper for Mac&lt;/a&gt; 
&lt;a href=&quot;http://www.hdvideoconverter-mac.com/dvd-maker-suite-for-mac.html&quot;&gt;DVD Maker Suite for Mac&lt;/a&gt; 
&lt;a href=&quot;http://www.hdvideoconverter-mac.com/dvd-creator-for-mac.html&quot;&gt;DVD Creator for Mac&lt;/a&gt; 	
&lt;a href=&quot;http://www.hdvideoconverter-mac.com/dvd-ripper-for-mac.html&quot;&gt;DVD Ripper for Mac&lt;/a&gt; 
&lt;a href=&quot;http://www.hdvideoconverter-mac.com/dvd-copy-for-mac.html&quot;&gt;DVD Copy for Mac&lt;/a&gt; 
&lt;a href=&quot;http://www.hdvideoconverter-mac.com/blu-ray-video-converter.html&quot;&gt;Blu-Ray Video Converter&lt;/a&gt;     
&lt;a href=&quot;http://www.hdvideoconverter-mac.com/dvd-converter.html&quot;&gt;DVD Converter&lt;/a&gt;  
&lt;a href=&quot;http://www.hdvideoconverter-mac.com/dvd-burner.html&quot;&gt;DVD Burner&lt;/a&gt;</body>
      <body-html>&lt;div&gt;&lt;p&gt;&lt;a href=&quot;http://www.hdvideoconverter-mac.com&quot;&gt;Video Converter
for Mac&lt;/a&gt;&lt;br&gt;
&lt;a href=
&quot;http://www.hdvideoconverter-mac.com/dvd-converter-for-mac.html&quot;&gt;DVD
Converter for Mac&lt;/a&gt;&lt;br&gt;
&lt;a href=
&quot;http://www.hdvideoconverter-mac.com/blu-ray-ripper-for-mac.html&quot;&gt;Blu-Ray
Ripper for Mac&lt;/a&gt;&lt;br&gt;
&lt;a href=
&quot;http://www.hdvideoconverter-mac.com/dvd-maker-suite-for-mac.html&quot;&gt;DVD
Maker Suite for Mac&lt;/a&gt;&lt;br&gt;
&lt;a href=
&quot;http://www.hdvideoconverter-mac.com/dvd-creator-for-mac.html&quot;&gt;DVD
Creator for Mac&lt;/a&gt;&lt;br&gt;
&lt;a href=
&quot;http://www.hdvideoconverter-mac.com/dvd-ripper-for-mac.html&quot;&gt;DVD
Ripper for Mac&lt;/a&gt;&lt;br&gt;
&lt;a href=
&quot;http://www.hdvideoconverter-mac.com/dvd-copy-for-mac.html&quot;&gt;DVD
Copy for Mac&lt;/a&gt;&lt;br&gt;
&lt;a href=
&quot;http://www.hdvideoconverter-mac.com/blu-ray-video-converter.html&quot;&gt;Blu-Ray
Video Converter&lt;/a&gt;&lt;br&gt;
&lt;a href=
&quot;http://www.hdvideoconverter-mac.com/dvd-converter.html&quot;&gt;DVD
Converter&lt;/a&gt;&lt;br&gt;
&lt;a href=&quot;http://www.hdvideoconverter-mac.com/dvd-burner.html&quot;&gt;DVD
Burner&lt;/a&gt;&lt;/p&gt;&lt;/div&gt;</body-html>
      <closed type="boolean">true</closed>
      <created-at type="datetime">2011-03-29T02:21:12+01:00</created-at>
      <creator-id type="integer">29265</creator-id>
      <diffable-attributes type="yaml">--- {}

</diffable-attributes>
      <milestone-id type="integer">9903</milestone-id>
      <number type="integer">2025</number>
      <permalink>add-a-check-for-reserved-words-in-generators</permalink>
      <priority type="integer">0</priority>
      <project-id type="integer">8994</project-id>
      <state>invalid</state>
      <tag nil="true"></tag>
      <title>add a check for reserved words in generators</title>
      <updated-at type="datetime">2011-03-29T02:29:22+01:00</updated-at>
      <user-id type="integer">143271</user-id>
      <version type="integer">8</version>
      <user-name>happy2011</user-name>
      <creator-name>kirillrdy</creator-name>
      <url>http://rails.lighthouseapp.com/projects/8994/tickets/2025</url>
      <milestone-title>2.x</milestone-title>
      <priority-name nil="true"></priority-name>
    </version>
  </versions>
</ticket>
