<?xml version="1.0" encoding="UTF-8"?>
<ticket>
  <assigned-user-id type="integer">12714</assigned-user-id>
  <attachments-count type="integer">0</attachments-count>
  <closed type="boolean">true</closed>
  <created-at type="datetime">2009-10-12T00:19:50+01:00</created-at>
  <creator-id type="integer">66995</creator-id>
  <milestone-due-on type="datetime" nil="true"></milestone-due-on>
  <milestone-id type="integer" nil="true"></milestone-id>
  <number type="integer">3366</number>
  <permalink>constant-actionviewbasesubclasses-maincontroller-not-defined</permalink>
  <priority type="integer">157580</priority>
  <project-id type="integer">8994</project-id>
  <raw-data type="binary" nil="true" encoding="base64"></raw-data>
  <state>stale</state>
  <tag nil="true"></tag>
  <title>constant ActionView::Base::Subclasses:: MainController not defined</title>
  <updated-at type="datetime">2010-10-06T06:40:34+01:00</updated-at>
  <user-id type="integer">89656</user-id>
  <version type="integer">2</version>
  <user-name>Rohit Arondekar</user-name>
  <creator-name>Joshua Partogi</creator-name>
  <assigned-user-name>Yehuda Katz (wycats)</assigned-user-name>
  <url>http://rails.lighthouseapp.com/projects/8994/tickets/3366</url>
  <priority-name nil="true"></priority-name>
  <original-body>Today I checked out the latest version 3.0 and it currently breaks my app. When I open my app from the browser I encounter this error: 

`NameError in MainController#index 
constant ActionView::Base::Subclasses::MainController not defined 
/rails/actionpack/lib/action_view/base.rb:242:in `remove_const' 
When I go to action_view/base.rb and remarked this line: 
Subclasses.class_eval do 
   remove_const(name) if const_defined?(name) 
   const_set(name, self) 
end`

It seems to work fine again. 
There seems to be an unfinished work there because I saw this comment line: 
`#Decouple this so helpers are a separate concern in AV just like.`</original-body>
  <latest-body>Today I checked out the latest version 3.0 and it currently breaks my app. When I open my app from the browser I encounter this error: 

`NameError in MainController#index 
constant ActionView::Base::Subclasses::MainController not defined 
/rails/actionpack/lib/action_view/base.rb:242:in `remove_const' 
When I go to action_view/base.rb and remarked this line: 
Subclasses.class_eval do 
   remove_const(name) if const_defined?(name) 
   const_set(name, self) 
end`

It seems to work fine again. 
There seems to be an unfinished work there because I saw this comment line: 
`#Decouple this so helpers are a separate concern in AV just like.`</latest-body>
  <original-body-html>&lt;div&gt;&lt;p&gt;Today I checked out the latest version 3.0 and it currently
breaks my app. When I open my app from the browser I encounter this
error:&lt;/p&gt;
&lt;p&gt;&lt;code&gt;NameError in MainController#index constant
ActionView::Base::Subclasses::MainController not defined&amp;lt;br/&amp;gt;
/rails/actionpack/lib/action_view/base.rb:242:in&lt;/code&gt;remove_const'
When I go to action_view/base.rb and remarked this line:&lt;br&gt;
Subclasses.class_eval do&lt;br&gt;
remove_const(name) if const_defined?(name) const_set(name, self)
end&lt;/p&gt;
&lt;p&gt;It seems to work fine again.&lt;br&gt;
There seems to be an unfinished work there because I saw this
comment line:&lt;br&gt;
&lt;code&gt;#Decouple this so helpers are a separate concern in AV just
like.&lt;/code&gt;&lt;/p&gt;&lt;/div&gt;</original-body-html>
  <versions type="array">
    <version type="Ticket::Version">
      <assigned-user-id type="integer">12714</assigned-user-id>
      <attachments-count type="integer">0</attachments-count>
      <body>Today I checked out the latest version 3.0 and it currently breaks my app. When I open my app from the browser I encounter this error: 

`NameError in MainController#index 
constant ActionView::Base::Subclasses::MainController not defined 
/rails/actionpack/lib/action_view/base.rb:242:in `remove_const' 
When I go to action_view/base.rb and remarked this line: 
Subclasses.class_eval do 
   remove_const(name) if const_defined?(name) 
   const_set(name, self) 
end`

It seems to work fine again. 
There seems to be an unfinished work there because I saw this comment line: 
`#Decouple this so helpers are a separate concern in AV just like.`</body>
      <body-html>&lt;div&gt;&lt;p&gt;Today I checked out the latest version 3.0 and it currently
breaks my app. When I open my app from the browser I encounter this
error:&lt;/p&gt;
&lt;p&gt;&lt;code&gt;NameError in MainController#index constant
ActionView::Base::Subclasses::MainController not defined&amp;lt;br/&amp;gt;
/rails/actionpack/lib/action_view/base.rb:242:in&lt;/code&gt;remove_const'
When I go to action_view/base.rb and remarked this line:&lt;br&gt;
Subclasses.class_eval do&lt;br&gt;
remove_const(name) if const_defined?(name) const_set(name, self)
end&lt;/p&gt;
&lt;p&gt;It seems to work fine again.&lt;br&gt;
There seems to be an unfinished work there because I saw this
comment line:&lt;br&gt;
&lt;code&gt;#Decouple this so helpers are a separate concern in AV just
like.&lt;/code&gt;&lt;/p&gt;&lt;/div&gt;</body-html>
      <closed type="boolean">false</closed>
      <created-at type="datetime">2009-10-12T00:19:50+01:00</created-at>
      <creator-id type="integer">66995</creator-id>
      <diffable-attributes type="yaml">--- {}

</diffable-attributes>
      <milestone-id type="integer" nil="true"></milestone-id>
      <number type="integer">3366</number>
      <permalink>constant-actionviewbasesubclasses-maincontroller-not-defined</permalink>
      <priority type="integer">0</priority>
      <project-id type="integer">8994</project-id>
      <state>new</state>
      <tag nil="true"></tag>
      <title>constant ActionView::Base::Subclasses:: MainController not defined</title>
      <updated-at type="datetime">2009-10-12T00:19:52+01:00</updated-at>
      <user-id type="integer">66995</user-id>
      <version type="integer">1</version>
      <user-name>Joshua Partogi</user-name>
      <creator-name>Joshua Partogi</creator-name>
      <assigned-user-name>Yehuda Katz (wycats)</assigned-user-name>
      <url>http://rails.lighthouseapp.com/projects/8994/tickets/3366</url>
      <priority-name nil="true"></priority-name>
    </version>
    <version type="Ticket::Version">
      <assigned-user-id type="integer">12714</assigned-user-id>
      <attachments-count type="integer">0</attachments-count>
      <body>Marking ticket as stale. If this is still an issue please leave a comment with suggested changes, creating a patch with tests, rebasing an existing patch or just confirming the issue on a latest release or master/branches.</body>
      <body-html>&lt;div&gt;&lt;p&gt;Marking ticket as stale. If this is still an issue please leave
a comment with suggested changes, creating a patch with tests,
rebasing an existing patch or just confirming the issue on a latest
release or master/branches.&lt;/p&gt;&lt;/div&gt;</body-html>
      <closed type="boolean">true</closed>
      <created-at type="datetime">2010-10-06T06:40:32+01:00</created-at>
      <creator-id type="integer">66995</creator-id>
      <diffable-attributes type="yaml">--- 
:priority: 0
:state: new
</diffable-attributes>
      <milestone-id type="integer" nil="true"></milestone-id>
      <number type="integer">3366</number>
      <permalink>constant-actionviewbasesubclasses-maincontroller-not-defined</permalink>
      <priority type="integer">157580</priority>
      <project-id type="integer">8994</project-id>
      <state>stale</state>
      <tag nil="true"></tag>
      <title>constant ActionView::Base::Subclasses:: MainController not defined</title>
      <updated-at type="datetime">2010-10-06T06:40:34+01:00</updated-at>
      <user-id type="integer">89656</user-id>
      <version type="integer">2</version>
      <user-name>Rohit Arondekar</user-name>
      <creator-name>Joshua Partogi</creator-name>
      <assigned-user-name>Yehuda Katz (wycats)</assigned-user-name>
      <url>http://rails.lighthouseapp.com/projects/8994/tickets/3366</url>
      <priority-name nil="true"></priority-name>
    </version>
  </versions>
</ticket>
