<?xml version="1.0" encoding="UTF-8"?>
<ticket>
  <assigned-user-id type="integer" nil="true"></assigned-user-id>
  <attachments-count type="integer">0</attachments-count>
  <closed type="boolean">true</closed>
  <created-at type="datetime">2010-08-06T19:30:50+01:00</created-at>
  <creator-id type="integer">72273</creator-id>
  <milestone-due-on type="datetime" nil="true"></milestone-due-on>
  <milestone-id type="integer" nil="true"></milestone-id>
  <number type="integer">5320</number>
  <permalink>actiondispatchtestresponse-duplicates-rackresponse-functionality</permalink>
  <priority type="integer">0</priority>
  <project-id type="integer">8994</project-id>
  <raw-data type="binary" nil="true" encoding="base64"></raw-data>
  <state>resolved</state>
  <tag nil="true"></tag>
  <title>ActionDispatch::TestResponse duplicates Rack::Response functionality</title>
  <updated-at type="datetime">2010-09-25T10:02:04+01:00</updated-at>
  <user-id type="integer">17393</user-id>
  <version type="integer">4</version>
  <user-name>Repository</user-name>
  <creator-name>John Firebaugh</creator-name>
  <url>http://rails.lighthouseapp.com/projects/8994/tickets/5320</url>
  <priority-name nil="true"></priority-name>
  <original-body>Rack::Response::Helpers (included in Rack::Response) provides #successful?, #redirection?, #client_error?, #server_error?, and #not_found?, with identical semantics to equivalent ActionDispatch::TestResponse methods.

Therefore:

* success? can be aliased to successful? or deprecated.
* missing? can be aliased to not_found? or deprecated.
* redirect? can be aliased to redirection? or deprecated.
* client_error? and server_error? can be removed.
* error? can be aliased to server_error? or deprecated.

If we deprecate these methods, .from_response will remain the only non-deprecated functionality provided by ActionDispatch::TestResponse.</original-body>
  <latest-body>Rack::Response::Helpers (included in Rack::Response) provides #successful?, #redirection?, #client_error?, #server_error?, and #not_found?, with identical semantics to equivalent ActionDispatch::TestResponse methods.

Therefore:

* success? can be aliased to successful? or deprecated.
* missing? can be aliased to not_found? or deprecated.
* redirect? can be aliased to redirection? or deprecated.
* client_error? and server_error? can be removed.
* error? can be aliased to server_error? or deprecated.

If we deprecate these methods, .from_response will remain the only non-deprecated functionality provided by ActionDispatch::TestResponse.</latest-body>
  <original-body-html>&lt;div&gt;&lt;p&gt;Rack::Response::Helpers (included in Rack::Response) provides
#successful?, #redirection?, #client_error?, #server_error?, and
#not_found?, with identical semantics to equivalent
ActionDispatch::TestResponse methods.&lt;/p&gt;
&lt;p&gt;Therefore:&lt;/p&gt;
&lt;ul&gt;
&lt;li&gt;success? can be aliased to successful? or deprecated.&lt;/li&gt;
&lt;li&gt;missing? can be aliased to not_found? or deprecated.&lt;/li&gt;
&lt;li&gt;redirect? can be aliased to redirection? or deprecated.&lt;/li&gt;
&lt;li&gt;client_error? and server_error? can be removed.&lt;/li&gt;
&lt;li&gt;error? can be aliased to server_error? or deprecated.&lt;/li&gt;
&lt;/ul&gt;
&lt;p&gt;If we deprecate these methods, .from_response will remain the
only non-deprecated functionality provided by
ActionDispatch::TestResponse.&lt;/p&gt;&lt;/div&gt;</original-body-html>
  <versions type="array">
    <version type="Ticket::Version">
      <assigned-user-id type="integer" nil="true"></assigned-user-id>
      <attachments-count type="integer">0</attachments-count>
      <body>Rack::Response::Helpers (included in Rack::Response) provides #successful?, #redirection?, #client_error?, #server_error?, and #not_found?, with identical semantics to equivalent ActionDispatch::TestResponse methods.

Therefore:

* success? can be aliased to successful? or deprecated.
* missing? can be aliased to not_found? or deprecated.
* redirect? can be aliased to redirection? or deprecated.
* client_error? and server_error? can be removed.
* error? can be aliased to server_error? or deprecated.

If we deprecate these methods, .from_response will remain the only non-deprecated functionality provided by ActionDispatch::TestResponse.</body>
      <body-html>&lt;div&gt;&lt;p&gt;Rack::Response::Helpers (included in Rack::Response) provides
#successful?, #redirection?, #client_error?, #server_error?, and
#not_found?, with identical semantics to equivalent
ActionDispatch::TestResponse methods.&lt;/p&gt;
&lt;p&gt;Therefore:&lt;/p&gt;
&lt;ul&gt;
&lt;li&gt;success? can be aliased to successful? or deprecated.&lt;/li&gt;
&lt;li&gt;missing? can be aliased to not_found? or deprecated.&lt;/li&gt;
&lt;li&gt;redirect? can be aliased to redirection? or deprecated.&lt;/li&gt;
&lt;li&gt;client_error? and server_error? can be removed.&lt;/li&gt;
&lt;li&gt;error? can be aliased to server_error? or deprecated.&lt;/li&gt;
&lt;/ul&gt;
&lt;p&gt;If we deprecate these methods, .from_response will remain the
only non-deprecated functionality provided by
ActionDispatch::TestResponse.&lt;/p&gt;&lt;/div&gt;</body-html>
      <closed type="boolean">false</closed>
      <created-at type="datetime">2010-08-06T19:30:50+01:00</created-at>
      <creator-id type="integer">72273</creator-id>
      <diffable-attributes type="yaml">--- {}

</diffable-attributes>
      <milestone-id type="integer" nil="true"></milestone-id>
      <number type="integer">5320</number>
      <permalink>actiondispatchtestresponse-duplicates-rackresponse-functionality</permalink>
      <priority type="integer">0</priority>
      <project-id type="integer">8994</project-id>
      <state>new</state>
      <tag nil="true"></tag>
      <title>ActionDispatch::TestResponse duplicates Rack::Response functionality</title>
      <updated-at type="datetime">2010-08-06T19:30:52+01:00</updated-at>
      <user-id type="integer">72273</user-id>
      <version type="integer">1</version>
      <user-name>John Firebaugh</user-name>
      <creator-name>John Firebaugh</creator-name>
      <url>http://rails.lighthouseapp.com/projects/8994/tickets/5320</url>
      <priority-name nil="true"></priority-name>
    </version>
    <version type="Ticket::Version">
      <assigned-user-id type="integer" nil="true"></assigned-user-id>
      <attachments-count type="integer">0</attachments-count>
      <body>Patches with aliasing: http://github.com/bigfix/rails/commits/8994</body>
      <body-html>&lt;div&gt;&lt;p&gt;Patches with aliasing: &lt;a href=
&quot;http://github.com/bigfix/rails/commits/8994&quot;&gt;http://github.com/bigfix/rails/commits/8994&lt;/a&gt;&lt;/p&gt;&lt;/div&gt;</body-html>
      <closed type="boolean">false</closed>
      <created-at type="datetime">2010-08-06T19:32:46+01:00</created-at>
      <creator-id type="integer">72273</creator-id>
      <diffable-attributes type="yaml">--- {}

</diffable-attributes>
      <milestone-id type="integer" nil="true"></milestone-id>
      <number type="integer">5320</number>
      <permalink>actiondispatchtestresponse-duplicates-rackresponse-functionality</permalink>
      <priority type="integer">0</priority>
      <project-id type="integer">8994</project-id>
      <state>new</state>
      <tag nil="true"></tag>
      <title>ActionDispatch::TestResponse duplicates Rack::Response functionality</title>
      <updated-at type="datetime">2010-08-06T19:32:48+01:00</updated-at>
      <user-id type="integer">72273</user-id>
      <version type="integer">2</version>
      <user-name>John Firebaugh</user-name>
      <creator-name>John Firebaugh</creator-name>
      <url>http://rails.lighthouseapp.com/projects/8994/tickets/5320</url>
      <priority-name nil="true"></priority-name>
    </version>
    <version type="Ticket::Version">
      <assigned-user-id type="integer" nil="true"></assigned-user-id>
      <attachments-count type="integer">0</attachments-count>
      <body>Whoops, meant to use the ticket number: http://github.com/bigfix/rails/commits/5320</body>
      <body-html>&lt;div&gt;&lt;p&gt;Whoops, meant to use the ticket number: &lt;a href=
&quot;http://github.com/bigfix/rails/commits/5320&quot;&gt;http://github.com/bigfix/rails/commits/5320&lt;/a&gt;&lt;/p&gt;&lt;/div&gt;</body-html>
      <closed type="boolean">false</closed>
      <created-at type="datetime">2010-08-06T19:34:20+01:00</created-at>
      <creator-id type="integer">72273</creator-id>
      <diffable-attributes type="yaml">--- {}

</diffable-attributes>
      <milestone-id type="integer" nil="true"></milestone-id>
      <number type="integer">5320</number>
      <permalink>actiondispatchtestresponse-duplicates-rackresponse-functionality</permalink>
      <priority type="integer">0</priority>
      <project-id type="integer">8994</project-id>
      <state>new</state>
      <tag nil="true"></tag>
      <title>ActionDispatch::TestResponse duplicates Rack::Response functionality</title>
      <updated-at type="datetime">2010-08-06T19:34:23+01:00</updated-at>
      <user-id type="integer">72273</user-id>
      <version type="integer">3</version>
      <user-name>John Firebaugh</user-name>
      <creator-name>John Firebaugh</creator-name>
      <url>http://rails.lighthouseapp.com/projects/8994/tickets/5320</url>
      <priority-name nil="true"></priority-name>
    </version>
    <version type="Ticket::Version">
      <assigned-user-id type="integer" nil="true"></assigned-user-id>
      <attachments-count type="integer">0</attachments-count>
      <body>(from [308517e913ef1e8d9f13e023bc450374b5ed780a]) Don't duplicate Rack::Response functionality. [#5320 state:resolved]

Signed-off-by: Jos&#233; Valim &lt;jose.valim@gmail.com&gt;
http://github.com/rails/rails/commit/308517e913ef1e8d9f13e023bc450374b5ed780a</body>
      <body-html>&lt;div&gt;&lt;p&gt;(from &lt;a href=
&quot;/projects/8994/changesets/308517e913ef1e8d9f13e023bc450374b5ed780a&quot;
title=
&quot;Changeset [308517e913ef1e8d9f13e023bc450374b5ed780a]&quot;&gt;[308517e913ef1e8d9f13e023bc450374b5ed780a]&lt;/a&gt;)
Don't duplicate Rack::Response functionality. [&lt;a href=
&quot;/projects/8994/tickets/5320&quot; title=&quot;Ticket #5320&quot;&gt;#5320&lt;/a&gt;
state:resolved]&lt;/p&gt;
&lt;p&gt;Signed-off-by: Jos&amp;eacute; Valim &lt;a&gt;jose.valim@gmail.com&lt;/a&gt;&lt;br&gt;
&lt;a href=
&quot;http://github.com/rails/rails/commit/308517e913ef1e8d9f13e023bc450374b5ed780a&quot;&gt;
http://github.com/rails/rails/commit/308517e913ef1e8d9f13e023bc4503...&lt;/a&gt;&lt;/p&gt;&lt;/div&gt;</body-html>
      <closed type="boolean">true</closed>
      <created-at type="datetime">2010-09-25T10:02:01+01:00</created-at>
      <creator-id type="integer">72273</creator-id>
      <diffable-attributes type="yaml">--- 
:state: new
</diffable-attributes>
      <milestone-id type="integer" nil="true"></milestone-id>
      <number type="integer">5320</number>
      <permalink>actiondispatchtestresponse-duplicates-rackresponse-functionality</permalink>
      <priority type="integer">0</priority>
      <project-id type="integer">8994</project-id>
      <state>resolved</state>
      <tag nil="true"></tag>
      <title>ActionDispatch::TestResponse duplicates Rack::Response functionality</title>
      <updated-at type="datetime">2010-09-25T10:02:04+01:00</updated-at>
      <user-id type="integer">17393</user-id>
      <version type="integer">4</version>
      <user-name>Repository</user-name>
      <creator-name>John Firebaugh</creator-name>
      <url>http://rails.lighthouseapp.com/projects/8994/tickets/5320</url>
      <priority-name nil="true"></priority-name>
    </version>
  </versions>
</ticket>
