<?xml version="1.0" encoding="UTF-8"?>
<ticket>
  <assigned-user-id type="integer" nil="true"></assigned-user-id>
  <attachments-count type="integer">0</attachments-count>
  <closed type="boolean">true</closed>
  <created-at type="datetime">2010-09-03T16:06:18+01:00</created-at>
  <creator-id type="integer">91469</creator-id>
  <milestone-due-on type="datetime" nil="true"></milestone-due-on>
  <milestone-id type="integer" nil="true"></milestone-id>
  <number type="integer">5549</number>
  <permalink>activerecordcalculationscount-not-work-when-mysql-table-is-empty</permalink>
  <priority type="integer">3</priority>
  <project-id type="integer">8994</project-id>
  <raw-data type="binary" nil="true" encoding="base64"></raw-data>
  <state>stale</state>
  <tag>&quot;activerecord  calculation&quot;</tag>
  <title>ActiveRecord::Calculations.count( )  not work , when mysql table is empty</title>
  <updated-at type="datetime">2011-02-02T16:53:31+00:00</updated-at>
  <user-id type="integer">40272</user-id>
  <version type="integer">9</version>
  <user-name>Santiago Pastorino</user-name>
  <creator-name>Hunter</creator-name>
  <url>http://rails.lighthouseapp.com/projects/8994/tickets/5549</url>
  <priority-name>Low</priority-name>
  <original-body>it can works well in rails2.3.5, now failed in rails3, it getting bad.


C:/Ruby192/lib/ruby/gems/1.9.1/gems/activerecord-3.0.0/lib/active_record/connect
ion_adapters/mysql_adapter.rb:629:in `select': undefined method `all_hashes' for
 #&lt;Mysql::Result:0x19b94c8&gt; (NoMethodError)
        from C:/Ruby192/lib/ruby/gems/1.9.1/gems/activerecord-3.0.0/lib/active_r
ecord/connection_adapters/abstract/database_statements.rb:7:in `select_all'
        from C:/Ruby192/lib/ruby/gems/1.9.1/gems/activerecord-3.0.0/lib/active_r
ecord/connection_adapters/abstract/query_cache.rb:56:in `select_all'
        from C:/Ruby192/lib/ruby/gems/1.9.1/gems/activerecord-3.0.0/lib/active_r
ecord/connection_adapters/abstract/database_statements.rb:13:in `select_one'
        from C:/Ruby192/lib/ruby/gems/1.9.1/gems/activerecord-3.0.0/lib/active_r
ecord/connection_adapters/abstract/database_statements.rb:19:in `select_value'
        from C:/Ruby192/lib/ruby/gems/1.9.1/gems/activerecord-3.0.0/lib/active_r
ecord/relation/calculations.rb:196:in `execute_simple_calculation'
        from C:/Ruby192/lib/ruby/gems/1.9.1/gems/activerecord-3.0.0/lib/active_r
ecord/relation/calculations.rb:183:in `perform_calculation'
        from C:/Ruby192/lib/ruby/gems/1.9.1/gems/activerecord-3.0.0/lib/active_r
ecord/relation/calculations.rb:152:in `calculate'
        from C:/Ruby192/lib/ruby/gems/1.9.1/gems/activerecord-3.0.0/lib/active_r
ecord/relation/calculations.rb:58:in `count'
        from C:in `count'
        from D:/vob/g2/config/initializers/cargo_category_load.rb:95:in `&lt;top (r
equired)&gt;'
        from C:/Ruby192/lib/ruby/gems/1.9.1/gems/activesupport-3.0.0/lib/active_
support/dependencies.rb:235:in `load'
        from C:/Ruby192/lib/ruby/gems/1.9.1/gems/activesupport-3.0.0/lib/active_
support/dependencies.rb:235:in `block in load'
        from C:/Ruby192/lib/ruby/gems/1.9.1/gems/activesupport-3.0.0/lib/active_
support/dependencies.rb:225:in `block in load_dependency'
        from C:/Ruby192/lib/ruby/gems/1.9.1/gems/activesupport-3.0.0/lib/active_
support/dependencies.rb:591:in `new_constants_in'
        from C:/Ruby192/lib/ruby/gems/1.9.1/gems/activesupport-3.0.0/lib/active_
support/dependencies.rb:225:in `load_dependency'
        from C:/Ruby192/lib/ruby/gems/1.9.1/gems/activesupport-3.0.0/lib/active_
support/dependencies.rb:235:in `load'
        from C:/Ruby192/lib/ruby/gems/1.9.1/gems/railties-3.0.0/lib/rails/engine
.rb:201:in `block (2 levels) in &lt;class:Engine&gt;'
        from C:/Ruby192/lib/ruby/gems/1.9.1/gems/railties-3.0.0/lib/rails/engine
.rb:200:in `each'
        from C:/Ruby192/lib/ruby/gems/1.9.1/gems/railties-3.0.0/lib/rails/engine
.rb:200:in `block in &lt;class:Engine&gt;'
        from C:/Ruby192/lib/ruby/gems/1.9.1/gems/railties-3.0.0/lib/rails/initia
lizable.rb:25:in `instance_exec'
        from C:/Ruby192/lib/ruby/gems/1.9.1/gems/railties-3.0.0/lib/rails/initia
lizable.rb:25:in `run'
        from C:/Ruby192/lib/ruby/gems/1.9.1/gems/railties-3.0.0/lib/rails/initia
lizable.rb:50:in `block in run_initializers'
        from C:/Ruby192/lib/ruby/gems/1.9.1/gems/railties-3.0.0/lib/rails/initia
lizable.rb:49:in `each'
        from C:/Ruby192/lib/ruby/gems/1.9.1/gems/railties-3.0.0/lib/rails/initia
lizable.rb:49:in `run_initializers'
        from C:/Ruby192/lib/ruby/gems/1.9.1/gems/railties-3.0.0/lib/rails/applic
ation.rb:134:in `initialize!'
        from C:/Ruby192/lib/ruby/gems/1.9.1/gems/railties-3.0.0/lib/rails/applic
ation.rb:77:in `method_missing'
        from D:/vob/g2/config/environment.rb:5:in `&lt;top (required)&gt;'
        from D:/vob/g2/config.ru:3:in `require'
        from D:/vob/g2/config.ru:3:in `block in &lt;main&gt;'
        from C:/Ruby192/lib/ruby/gems/1.9.1/gems/rack-1.2.1/lib/rack/builder.rb:
46:in `instance_eval'
        from C:/Ruby192/lib/ruby/gems/1.9.1/gems/rack-1.2.1/lib/rack/builder.rb:
46:in `initialize'
        from D:/vob/g2/config.ru:1:in `new'
        from D:/vob/g2/config.ru:1:in `&lt;main&gt;'
        from C:/Ruby192/lib/ruby/gems/1.9.1/gems/rack-1.2.1/lib/rack/builder.rb:
35:in `eval'
        from C:/Ruby192/lib/ruby/gems/1.9.1/gems/rack-1.2.1/lib/rack/builder.rb:
35:in `parse_file'
        from C:/Ruby192/lib/ruby/gems/1.9.1/gems/rack-1.2.1/lib/rack/server.rb:1
62:in `app'
        from C:/Ruby192/lib/ruby/gems/1.9.1/gems/rack-1.2.1/lib/rack/server.rb:2
48:in `wrapped_app'
        from C:/Ruby192/lib/ruby/gems/1.9.1/gems/rack-1.2.1/lib/rack/server.rb:2
13:in `start'
        from C:/Ruby192/lib/ruby/gems/1.9.1/gems/railties-3.0.0/lib/rails/comman
ds/server.rb:65:in `start'
        from C:/Ruby192/lib/ruby/gems/1.9.1/gems/railties-3.0.0/lib/rails/comman
ds.rb:30:in `block in &lt;top (required)&gt;'
        from C:/Ruby192/lib/ruby/gems/1.9.1/gems/railties-3.0.0/lib/rails/comman
ds.rb:27:in `tap'
        from C:/Ruby192/lib/ruby/gems/1.9.1/gems/railties-3.0.0/lib/rails/comman
ds.rb:27:in `&lt;top (required)&gt;'
        from script/rails:6:in `require'
        from script/rails:6:in `&lt;main&gt;'</original-body>
  <latest-body>it can works well in rails2.3.5, now failed in rails3, it getting bad.


C:/Ruby192/lib/ruby/gems/1.9.1/gems/activerecord-3.0.0/lib/active_record/connect
ion_adapters/mysql_adapter.rb:629:in `select': undefined method `all_hashes' for
 #&lt;Mysql::Result:0x19b94c8&gt; (NoMethodError)
        from C:/Ruby192/lib/ruby/gems/1.9.1/gems/activerecord-3.0.0/lib/active_r
ecord/connection_adapters/abstract/database_statements.rb:7:in `select_all'
        from C:/Ruby192/lib/ruby/gems/1.9.1/gems/activerecord-3.0.0/lib/active_r
ecord/connection_adapters/abstract/query_cache.rb:56:in `select_all'
        from C:/Ruby192/lib/ruby/gems/1.9.1/gems/activerecord-3.0.0/lib/active_r
ecord/connection_adapters/abstract/database_statements.rb:13:in `select_one'
        from C:/Ruby192/lib/ruby/gems/1.9.1/gems/activerecord-3.0.0/lib/active_r
ecord/connection_adapters/abstract/database_statements.rb:19:in `select_value'
        from C:/Ruby192/lib/ruby/gems/1.9.1/gems/activerecord-3.0.0/lib/active_r
ecord/relation/calculations.rb:196:in `execute_simple_calculation'
        from C:/Ruby192/lib/ruby/gems/1.9.1/gems/activerecord-3.0.0/lib/active_r
ecord/relation/calculations.rb:183:in `perform_calculation'
        from C:/Ruby192/lib/ruby/gems/1.9.1/gems/activerecord-3.0.0/lib/active_r
ecord/relation/calculations.rb:152:in `calculate'
        from C:/Ruby192/lib/ruby/gems/1.9.1/gems/activerecord-3.0.0/lib/active_r
ecord/relation/calculations.rb:58:in `count'
        from C:in `count'
        from D:/vob/g2/config/initializers/cargo_category_load.rb:95:in `&lt;top (r
equired)&gt;'
        from C:/Ruby192/lib/ruby/gems/1.9.1/gems/activesupport-3.0.0/lib/active_
support/dependencies.rb:235:in `load'
        from C:/Ruby192/lib/ruby/gems/1.9.1/gems/activesupport-3.0.0/lib/active_
support/dependencies.rb:235:in `block in load'
        from C:/Ruby192/lib/ruby/gems/1.9.1/gems/activesupport-3.0.0/lib/active_
support/dependencies.rb:225:in `block in load_dependency'
        from C:/Ruby192/lib/ruby/gems/1.9.1/gems/activesupport-3.0.0/lib/active_
support/dependencies.rb:591:in `new_constants_in'
        from C:/Ruby192/lib/ruby/gems/1.9.1/gems/activesupport-3.0.0/lib/active_
support/dependencies.rb:225:in `load_dependency'
        from C:/Ruby192/lib/ruby/gems/1.9.1/gems/activesupport-3.0.0/lib/active_
support/dependencies.rb:235:in `load'
        from C:/Ruby192/lib/ruby/gems/1.9.1/gems/railties-3.0.0/lib/rails/engine
.rb:201:in `block (2 levels) in &lt;class:Engine&gt;'
        from C:/Ruby192/lib/ruby/gems/1.9.1/gems/railties-3.0.0/lib/rails/engine
.rb:200:in `each'
        from C:/Ruby192/lib/ruby/gems/1.9.1/gems/railties-3.0.0/lib/rails/engine
.rb:200:in `block in &lt;class:Engine&gt;'
        from C:/Ruby192/lib/ruby/gems/1.9.1/gems/railties-3.0.0/lib/rails/initia
lizable.rb:25:in `instance_exec'
        from C:/Ruby192/lib/ruby/gems/1.9.1/gems/railties-3.0.0/lib/rails/initia
lizable.rb:25:in `run'
        from C:/Ruby192/lib/ruby/gems/1.9.1/gems/railties-3.0.0/lib/rails/initia
lizable.rb:50:in `block in run_initializers'
        from C:/Ruby192/lib/ruby/gems/1.9.1/gems/railties-3.0.0/lib/rails/initia
lizable.rb:49:in `each'
        from C:/Ruby192/lib/ruby/gems/1.9.1/gems/railties-3.0.0/lib/rails/initia
lizable.rb:49:in `run_initializers'
        from C:/Ruby192/lib/ruby/gems/1.9.1/gems/railties-3.0.0/lib/rails/applic
ation.rb:134:in `initialize!'
        from C:/Ruby192/lib/ruby/gems/1.9.1/gems/railties-3.0.0/lib/rails/applic
ation.rb:77:in `method_missing'
        from D:/vob/g2/config/environment.rb:5:in `&lt;top (required)&gt;'
        from D:/vob/g2/config.ru:3:in `require'
        from D:/vob/g2/config.ru:3:in `block in &lt;main&gt;'
        from C:/Ruby192/lib/ruby/gems/1.9.1/gems/rack-1.2.1/lib/rack/builder.rb:
46:in `instance_eval'
        from C:/Ruby192/lib/ruby/gems/1.9.1/gems/rack-1.2.1/lib/rack/builder.rb:
46:in `initialize'
        from D:/vob/g2/config.ru:1:in `new'
        from D:/vob/g2/config.ru:1:in `&lt;main&gt;'
        from C:/Ruby192/lib/ruby/gems/1.9.1/gems/rack-1.2.1/lib/rack/builder.rb:
35:in `eval'
        from C:/Ruby192/lib/ruby/gems/1.9.1/gems/rack-1.2.1/lib/rack/builder.rb:
35:in `parse_file'
        from C:/Ruby192/lib/ruby/gems/1.9.1/gems/rack-1.2.1/lib/rack/server.rb:1
62:in `app'
        from C:/Ruby192/lib/ruby/gems/1.9.1/gems/rack-1.2.1/lib/rack/server.rb:2
48:in `wrapped_app'
        from C:/Ruby192/lib/ruby/gems/1.9.1/gems/rack-1.2.1/lib/rack/server.rb:2
13:in `start'
        from C:/Ruby192/lib/ruby/gems/1.9.1/gems/railties-3.0.0/lib/rails/comman
ds/server.rb:65:in `start'
        from C:/Ruby192/lib/ruby/gems/1.9.1/gems/railties-3.0.0/lib/rails/comman
ds.rb:30:in `block in &lt;top (required)&gt;'
        from C:/Ruby192/lib/ruby/gems/1.9.1/gems/railties-3.0.0/lib/rails/comman
ds.rb:27:in `tap'
        from C:/Ruby192/lib/ruby/gems/1.9.1/gems/railties-3.0.0/lib/rails/comman
ds.rb:27:in `&lt;top (required)&gt;'
        from script/rails:6:in `require'
        from script/rails:6:in `&lt;main&gt;'</latest-body>
  <original-body-html>&lt;div&gt;&lt;p&gt;it can works well in rails2.3.5, now failed in rails3, it
getting bad.&lt;/p&gt;
&lt;p&gt;
C:/Ruby192/lib/ruby/gems/1.9.1/gems/activerecord-3.0.0/lib/active_record/connect&lt;br&gt;
ion_adapters/mysql_adapter.rb:629:in &lt;code&gt;select': undefined
method&lt;/code&gt;all_hashes' for&lt;br&gt;
#&amp;lt;Mysql::Result:0x19b94c8&amp;gt; (NoMethodError)&lt;/p&gt;
&lt;pre&gt;
&lt;code&gt;    from C:/Ruby192/lib/ruby/gems/1.9.1/gems/activerecord-3.0.0/lib/active_r&lt;/code&gt;
&lt;/pre&gt;
&lt;p&gt;ecord/connection_adapters/abstract/database_statements.rb:7:in
&lt;code&gt;select_all'&amp;lt;br/&amp;gt;&lt;/code&gt;&lt;/p&gt;
&lt;pre&gt;
&lt;code&gt;    from C:/Ruby192/lib/ruby/gems/1.9.1/gems/activerecord-3.0.0/lib/active_r&lt;/code&gt;
&lt;/pre&gt;
&lt;p&gt;ecord/connection_adapters/abstract/query_cache.rb:56:in
&lt;code&gt;select_all'&amp;lt;br/&amp;gt;&lt;/code&gt;&lt;/p&gt;
&lt;pre&gt;
&lt;code&gt;    from C:/Ruby192/lib/ruby/gems/1.9.1/gems/activerecord-3.0.0/lib/active_r&lt;/code&gt;
&lt;/pre&gt;
&lt;p&gt;ecord/connection_adapters/abstract/database_statements.rb:13:in
&lt;code&gt;select_one'&amp;lt;br/&amp;gt;&lt;/code&gt;&lt;/p&gt;
&lt;pre&gt;
&lt;code&gt;    from C:/Ruby192/lib/ruby/gems/1.9.1/gems/activerecord-3.0.0/lib/active_r&lt;/code&gt;
&lt;/pre&gt;
&lt;p&gt;ecord/connection_adapters/abstract/database_statements.rb:19:in
&lt;code&gt;select_value'&amp;lt;br/&amp;gt;&lt;/code&gt;&lt;/p&gt;
&lt;pre&gt;
&lt;code&gt;    from C:/Ruby192/lib/ruby/gems/1.9.1/gems/activerecord-3.0.0/lib/active_r&lt;/code&gt;
&lt;/pre&gt;
&lt;p&gt;ecord/relation/calculations.rb:196:in
&lt;code&gt;execute_simple_calculation'&amp;lt;br/&amp;gt;&lt;/code&gt;&lt;/p&gt;
&lt;pre&gt;
&lt;code&gt;    from C:/Ruby192/lib/ruby/gems/1.9.1/gems/activerecord-3.0.0/lib/active_r&lt;/code&gt;
&lt;/pre&gt;
&lt;p&gt;ecord/relation/calculations.rb:183:in
&lt;code&gt;perform_calculation'&amp;lt;br/&amp;gt;&lt;/code&gt;&lt;/p&gt;
&lt;pre&gt;
&lt;code&gt;    from C:/Ruby192/lib/ruby/gems/1.9.1/gems/activerecord-3.0.0/lib/active_r&lt;/code&gt;
&lt;/pre&gt;
&lt;p&gt;ecord/relation/calculations.rb:152:in
&lt;code&gt;calculate'&amp;lt;br/&amp;gt;&lt;/code&gt;&lt;/p&gt;
&lt;pre&gt;
&lt;code&gt;    from C:/Ruby192/lib/ruby/gems/1.9.1/gems/activerecord-3.0.0/lib/active_r&lt;/code&gt;
&lt;/pre&gt;
&lt;p&gt;ecord/relation/calculations.rb:58:in
&lt;code&gt;count'&amp;lt;br/&amp;gt;&lt;/code&gt;&lt;/p&gt;
&lt;pre&gt;
&lt;code&gt;    from C:in `count'
    from D:/vob/g2/config/initializers/cargo_category_load.rb:95:in `&amp;lt;top (r&lt;/code&gt;
&lt;/pre&gt;
&lt;p&gt;equired)&amp;gt;'&lt;br&gt;&lt;/p&gt;
&lt;pre&gt;
&lt;code&gt;    from C:/Ruby192/lib/ruby/gems/1.9.1/gems/activesupport-3.0.0/lib/active_&lt;/code&gt;
&lt;/pre&gt;
&lt;p&gt;support/dependencies.rb:235:in &lt;code&gt;load'&amp;lt;br/&amp;gt;&lt;/code&gt;&lt;/p&gt;
&lt;pre&gt;
&lt;code&gt;    from C:/Ruby192/lib/ruby/gems/1.9.1/gems/activesupport-3.0.0/lib/active_&lt;/code&gt;
&lt;/pre&gt;
&lt;p&gt;support/dependencies.rb:235:in &lt;code&gt;block in
load'&amp;lt;br/&amp;gt;&lt;/code&gt;&lt;/p&gt;
&lt;pre&gt;
&lt;code&gt;    from C:/Ruby192/lib/ruby/gems/1.9.1/gems/activesupport-3.0.0/lib/active_&lt;/code&gt;
&lt;/pre&gt;
&lt;p&gt;support/dependencies.rb:225:in &lt;code&gt;block in
load_dependency'&amp;lt;br/&amp;gt;&lt;/code&gt;&lt;/p&gt;
&lt;pre&gt;
&lt;code&gt;    from C:/Ruby192/lib/ruby/gems/1.9.1/gems/activesupport-3.0.0/lib/active_&lt;/code&gt;
&lt;/pre&gt;
&lt;p&gt;support/dependencies.rb:591:in
&lt;code&gt;new_constants_in'&amp;lt;br/&amp;gt;&lt;/code&gt;&lt;/p&gt;
&lt;pre&gt;
&lt;code&gt;    from C:/Ruby192/lib/ruby/gems/1.9.1/gems/activesupport-3.0.0/lib/active_&lt;/code&gt;
&lt;/pre&gt;
&lt;p&gt;support/dependencies.rb:225:in
&lt;code&gt;load_dependency'&amp;lt;br/&amp;gt;&lt;/code&gt;&lt;/p&gt;
&lt;pre&gt;
&lt;code&gt;    from C:/Ruby192/lib/ruby/gems/1.9.1/gems/activesupport-3.0.0/lib/active_&lt;/code&gt;
&lt;/pre&gt;
&lt;p&gt;support/dependencies.rb:235:in &lt;code&gt;load'&amp;lt;br/&amp;gt;&lt;/code&gt;&lt;/p&gt;
&lt;pre&gt;
&lt;code&gt;    from C:/Ruby192/lib/ruby/gems/1.9.1/gems/railties-3.0.0/lib/rails/engine&lt;/code&gt;
&lt;/pre&gt;
&lt;p&gt;.rb:201:in &lt;code&gt;block (2 levels) in
&amp;lt;class:Engine&amp;gt;'&lt;/code&gt;&lt;/p&gt;
&lt;pre&gt;
&lt;code&gt;    from C:/Ruby192/lib/ruby/gems/1.9.1/gems/railties-3.0.0/lib/rails/engine&lt;/code&gt;
&lt;/pre&gt;
&lt;p&gt;.rb:200:in &lt;code&gt;each'&lt;/code&gt;&lt;/p&gt;
&lt;pre&gt;
&lt;code&gt;    from C:/Ruby192/lib/ruby/gems/1.9.1/gems/railties-3.0.0/lib/rails/engine&lt;/code&gt;
&lt;/pre&gt;
&lt;p&gt;.rb:200:in &lt;code&gt;block in &amp;lt;class:Engine&amp;gt;'&lt;/code&gt;&lt;/p&gt;
&lt;pre&gt;
&lt;code&gt;    from C:/Ruby192/lib/ruby/gems/1.9.1/gems/railties-3.0.0/lib/rails/initia&lt;/code&gt;
&lt;/pre&gt;
&lt;p&gt;lizable.rb:25:in &lt;code&gt;instance_exec'&amp;lt;br/&amp;gt;&lt;/code&gt;&lt;/p&gt;
&lt;pre&gt;
&lt;code&gt;    from C:/Ruby192/lib/ruby/gems/1.9.1/gems/railties-3.0.0/lib/rails/initia&lt;/code&gt;
&lt;/pre&gt;
&lt;p&gt;lizable.rb:25:in &lt;code&gt;run'&amp;lt;br/&amp;gt;&lt;/code&gt;&lt;/p&gt;
&lt;pre&gt;
&lt;code&gt;    from C:/Ruby192/lib/ruby/gems/1.9.1/gems/railties-3.0.0/lib/rails/initia&lt;/code&gt;
&lt;/pre&gt;
&lt;p&gt;lizable.rb:50:in &lt;code&gt;block in
run_initializers'&amp;lt;br/&amp;gt;&lt;/code&gt;&lt;/p&gt;
&lt;pre&gt;
&lt;code&gt;    from C:/Ruby192/lib/ruby/gems/1.9.1/gems/railties-3.0.0/lib/rails/initia&lt;/code&gt;
&lt;/pre&gt;
&lt;p&gt;lizable.rb:49:in &lt;code&gt;each'&amp;lt;br/&amp;gt;&lt;/code&gt;&lt;/p&gt;
&lt;pre&gt;
&lt;code&gt;    from C:/Ruby192/lib/ruby/gems/1.9.1/gems/railties-3.0.0/lib/rails/initia&lt;/code&gt;
&lt;/pre&gt;
&lt;p&gt;lizable.rb:49:in &lt;code&gt;run_initializers'&amp;lt;br/&amp;gt;&lt;/code&gt;&lt;/p&gt;
&lt;pre&gt;
&lt;code&gt;    from C:/Ruby192/lib/ruby/gems/1.9.1/gems/railties-3.0.0/lib/rails/applic&lt;/code&gt;
&lt;/pre&gt;
&lt;p&gt;ation.rb:134:in &lt;code&gt;initialize!'&amp;lt;br/&amp;gt;&lt;/code&gt;&lt;/p&gt;
&lt;pre&gt;
&lt;code&gt;    from C:/Ruby192/lib/ruby/gems/1.9.1/gems/railties-3.0.0/lib/rails/applic&lt;/code&gt;
&lt;/pre&gt;
&lt;p&gt;ation.rb:77:in &lt;code&gt;method_missing'&amp;lt;br/&amp;gt;&lt;/code&gt;&lt;/p&gt;
&lt;pre&gt;
&lt;code&gt;    from D:/vob/g2/config/environment.rb:5:in `&amp;lt;top (required)&amp;gt;'
    from D:/vob/g2/config.ru:3:in `require'
    from D:/vob/g2/config.ru:3:in `block in &amp;lt;main&amp;gt;'
    from C:/Ruby192/lib/ruby/gems/1.9.1/gems/rack-1.2.1/lib/rack/builder.rb:&lt;/code&gt;
&lt;/pre&gt;
&lt;p&gt;46:in &lt;code&gt;instance_eval'&amp;lt;br/&amp;gt;&lt;/code&gt;&lt;/p&gt;
&lt;pre&gt;
&lt;code&gt;    from C:/Ruby192/lib/ruby/gems/1.9.1/gems/rack-1.2.1/lib/rack/builder.rb:&lt;/code&gt;
&lt;/pre&gt;
&lt;p&gt;46:in &lt;code&gt;initialize'&amp;lt;br/&amp;gt;&lt;/code&gt;&lt;/p&gt;
&lt;pre&gt;
&lt;code&gt;    from D:/vob/g2/config.ru:1:in `new'
    from D:/vob/g2/config.ru:1:in `&amp;lt;main&amp;gt;'
    from C:/Ruby192/lib/ruby/gems/1.9.1/gems/rack-1.2.1/lib/rack/builder.rb:&lt;/code&gt;
&lt;/pre&gt;
&lt;p&gt;35:in &lt;code&gt;eval'&amp;lt;br/&amp;gt;&lt;/code&gt;&lt;/p&gt;
&lt;pre&gt;
&lt;code&gt;    from C:/Ruby192/lib/ruby/gems/1.9.1/gems/rack-1.2.1/lib/rack/builder.rb:&lt;/code&gt;
&lt;/pre&gt;
&lt;p&gt;35:in &lt;code&gt;parse_file'&amp;lt;br/&amp;gt;&lt;/code&gt;&lt;/p&gt;
&lt;pre&gt;
&lt;code&gt;    from C:/Ruby192/lib/ruby/gems/1.9.1/gems/rack-1.2.1/lib/rack/server.rb:1&lt;/code&gt;
&lt;/pre&gt;
&lt;p&gt;62:in &lt;code&gt;app'&amp;lt;br/&amp;gt;&lt;/code&gt;&lt;/p&gt;
&lt;pre&gt;
&lt;code&gt;    from C:/Ruby192/lib/ruby/gems/1.9.1/gems/rack-1.2.1/lib/rack/server.rb:2&lt;/code&gt;
&lt;/pre&gt;
&lt;p&gt;48:in &lt;code&gt;wrapped_app'&amp;lt;br/&amp;gt;&lt;/code&gt;&lt;/p&gt;
&lt;pre&gt;
&lt;code&gt;    from C:/Ruby192/lib/ruby/gems/1.9.1/gems/rack-1.2.1/lib/rack/server.rb:2&lt;/code&gt;
&lt;/pre&gt;
&lt;p&gt;13:in &lt;code&gt;start'&amp;lt;br/&amp;gt;&lt;/code&gt;&lt;/p&gt;
&lt;pre&gt;
&lt;code&gt;    from C:/Ruby192/lib/ruby/gems/1.9.1/gems/railties-3.0.0/lib/rails/comman&lt;/code&gt;
&lt;/pre&gt;
&lt;p&gt;ds/server.rb:65:in &lt;code&gt;start'&amp;lt;br/&amp;gt;&lt;/code&gt;&lt;/p&gt;
&lt;pre&gt;
&lt;code&gt;    from C:/Ruby192/lib/ruby/gems/1.9.1/gems/railties-3.0.0/lib/rails/comman&lt;/code&gt;
&lt;/pre&gt;
&lt;p&gt;ds.rb:30:in &lt;code&gt;block in &amp;lt;top
(required)&amp;gt;'&amp;lt;br/&amp;gt;&lt;/code&gt;&lt;/p&gt;
&lt;pre&gt;
&lt;code&gt;    from C:/Ruby192/lib/ruby/gems/1.9.1/gems/railties-3.0.0/lib/rails/comman&lt;/code&gt;
&lt;/pre&gt;
&lt;p&gt;ds.rb:27:in &lt;code&gt;tap'&amp;lt;br/&amp;gt;&lt;/code&gt;&lt;/p&gt;
&lt;pre&gt;
&lt;code&gt;    from C:/Ruby192/lib/ruby/gems/1.9.1/gems/railties-3.0.0/lib/rails/comman&lt;/code&gt;
&lt;/pre&gt;
&lt;p&gt;ds.rb:27:in &lt;code&gt;&amp;lt;top (required)&amp;gt;'&amp;lt;br/&amp;gt;&lt;/code&gt;&lt;/p&gt;
&lt;pre&gt;
&lt;code&gt;    from script/rails:6:in `require'
    from script/rails:6:in `&amp;lt;main&amp;gt;'&lt;/code&gt;
&lt;/pre&gt;&lt;/div&gt;</original-body-html>
  <versions type="array">
    <version type="Ticket::Version">
      <assigned-user-id type="integer" nil="true"></assigned-user-id>
      <attachments-count type="integer">0</attachments-count>
      <body>it can works well in rails2.3.5, now failed in rails3, it getting bad.


C:/Ruby192/lib/ruby/gems/1.9.1/gems/activerecord-3.0.0/lib/active_record/connect
ion_adapters/mysql_adapter.rb:629:in `select': undefined method `all_hashes' for
 #&lt;Mysql::Result:0x19b94c8&gt; (NoMethodError)
        from C:/Ruby192/lib/ruby/gems/1.9.1/gems/activerecord-3.0.0/lib/active_r
ecord/connection_adapters/abstract/database_statements.rb:7:in `select_all'
        from C:/Ruby192/lib/ruby/gems/1.9.1/gems/activerecord-3.0.0/lib/active_r
ecord/connection_adapters/abstract/query_cache.rb:56:in `select_all'
        from C:/Ruby192/lib/ruby/gems/1.9.1/gems/activerecord-3.0.0/lib/active_r
ecord/connection_adapters/abstract/database_statements.rb:13:in `select_one'
        from C:/Ruby192/lib/ruby/gems/1.9.1/gems/activerecord-3.0.0/lib/active_r
ecord/connection_adapters/abstract/database_statements.rb:19:in `select_value'
        from C:/Ruby192/lib/ruby/gems/1.9.1/gems/activerecord-3.0.0/lib/active_r
ecord/relation/calculations.rb:196:in `execute_simple_calculation'
        from C:/Ruby192/lib/ruby/gems/1.9.1/gems/activerecord-3.0.0/lib/active_r
ecord/relation/calculations.rb:183:in `perform_calculation'
        from C:/Ruby192/lib/ruby/gems/1.9.1/gems/activerecord-3.0.0/lib/active_r
ecord/relation/calculations.rb:152:in `calculate'
        from C:/Ruby192/lib/ruby/gems/1.9.1/gems/activerecord-3.0.0/lib/active_r
ecord/relation/calculations.rb:58:in `count'
        from C:in `count'
        from D:/vob/g2/config/initializers/cargo_category_load.rb:95:in `&lt;top (r
equired)&gt;'
        from C:/Ruby192/lib/ruby/gems/1.9.1/gems/activesupport-3.0.0/lib/active_
support/dependencies.rb:235:in `load'
        from C:/Ruby192/lib/ruby/gems/1.9.1/gems/activesupport-3.0.0/lib/active_
support/dependencies.rb:235:in `block in load'
        from C:/Ruby192/lib/ruby/gems/1.9.1/gems/activesupport-3.0.0/lib/active_
support/dependencies.rb:225:in `block in load_dependency'
        from C:/Ruby192/lib/ruby/gems/1.9.1/gems/activesupport-3.0.0/lib/active_
support/dependencies.rb:591:in `new_constants_in'
        from C:/Ruby192/lib/ruby/gems/1.9.1/gems/activesupport-3.0.0/lib/active_
support/dependencies.rb:225:in `load_dependency'
        from C:/Ruby192/lib/ruby/gems/1.9.1/gems/activesupport-3.0.0/lib/active_
support/dependencies.rb:235:in `load'
        from C:/Ruby192/lib/ruby/gems/1.9.1/gems/railties-3.0.0/lib/rails/engine
.rb:201:in `block (2 levels) in &lt;class:Engine&gt;'
        from C:/Ruby192/lib/ruby/gems/1.9.1/gems/railties-3.0.0/lib/rails/engine
.rb:200:in `each'
        from C:/Ruby192/lib/ruby/gems/1.9.1/gems/railties-3.0.0/lib/rails/engine
.rb:200:in `block in &lt;class:Engine&gt;'
        from C:/Ruby192/lib/ruby/gems/1.9.1/gems/railties-3.0.0/lib/rails/initia
lizable.rb:25:in `instance_exec'
        from C:/Ruby192/lib/ruby/gems/1.9.1/gems/railties-3.0.0/lib/rails/initia
lizable.rb:25:in `run'
        from C:/Ruby192/lib/ruby/gems/1.9.1/gems/railties-3.0.0/lib/rails/initia
lizable.rb:50:in `block in run_initializers'
        from C:/Ruby192/lib/ruby/gems/1.9.1/gems/railties-3.0.0/lib/rails/initia
lizable.rb:49:in `each'
        from C:/Ruby192/lib/ruby/gems/1.9.1/gems/railties-3.0.0/lib/rails/initia
lizable.rb:49:in `run_initializers'
        from C:/Ruby192/lib/ruby/gems/1.9.1/gems/railties-3.0.0/lib/rails/applic
ation.rb:134:in `initialize!'
        from C:/Ruby192/lib/ruby/gems/1.9.1/gems/railties-3.0.0/lib/rails/applic
ation.rb:77:in `method_missing'
        from D:/vob/g2/config/environment.rb:5:in `&lt;top (required)&gt;'
        from D:/vob/g2/config.ru:3:in `require'
        from D:/vob/g2/config.ru:3:in `block in &lt;main&gt;'
        from C:/Ruby192/lib/ruby/gems/1.9.1/gems/rack-1.2.1/lib/rack/builder.rb:
46:in `instance_eval'
        from C:/Ruby192/lib/ruby/gems/1.9.1/gems/rack-1.2.1/lib/rack/builder.rb:
46:in `initialize'
        from D:/vob/g2/config.ru:1:in `new'
        from D:/vob/g2/config.ru:1:in `&lt;main&gt;'
        from C:/Ruby192/lib/ruby/gems/1.9.1/gems/rack-1.2.1/lib/rack/builder.rb:
35:in `eval'
        from C:/Ruby192/lib/ruby/gems/1.9.1/gems/rack-1.2.1/lib/rack/builder.rb:
35:in `parse_file'
        from C:/Ruby192/lib/ruby/gems/1.9.1/gems/rack-1.2.1/lib/rack/server.rb:1
62:in `app'
        from C:/Ruby192/lib/ruby/gems/1.9.1/gems/rack-1.2.1/lib/rack/server.rb:2
48:in `wrapped_app'
        from C:/Ruby192/lib/ruby/gems/1.9.1/gems/rack-1.2.1/lib/rack/server.rb:2
13:in `start'
        from C:/Ruby192/lib/ruby/gems/1.9.1/gems/railties-3.0.0/lib/rails/comman
ds/server.rb:65:in `start'
        from C:/Ruby192/lib/ruby/gems/1.9.1/gems/railties-3.0.0/lib/rails/comman
ds.rb:30:in `block in &lt;top (required)&gt;'
        from C:/Ruby192/lib/ruby/gems/1.9.1/gems/railties-3.0.0/lib/rails/comman
ds.rb:27:in `tap'
        from C:/Ruby192/lib/ruby/gems/1.9.1/gems/railties-3.0.0/lib/rails/comman
ds.rb:27:in `&lt;top (required)&gt;'
        from script/rails:6:in `require'
        from script/rails:6:in `&lt;main&gt;'</body>
      <body-html>&lt;div&gt;&lt;p&gt;it can works well in rails2.3.5, now failed in rails3, it
getting bad.&lt;/p&gt;
&lt;p&gt;
C:/Ruby192/lib/ruby/gems/1.9.1/gems/activerecord-3.0.0/lib/active_record/connect&lt;br&gt;
ion_adapters/mysql_adapter.rb:629:in &lt;code&gt;select': undefined
method&lt;/code&gt;all_hashes' for&lt;br&gt;
#&amp;lt;Mysql::Result:0x19b94c8&amp;gt; (NoMethodError)&lt;/p&gt;
&lt;pre&gt;
&lt;code&gt;    from C:/Ruby192/lib/ruby/gems/1.9.1/gems/activerecord-3.0.0/lib/active_r&lt;/code&gt;
&lt;/pre&gt;
&lt;p&gt;ecord/connection_adapters/abstract/database_statements.rb:7:in
&lt;code&gt;select_all'&amp;lt;br/&amp;gt;&lt;/code&gt;&lt;/p&gt;
&lt;pre&gt;
&lt;code&gt;    from C:/Ruby192/lib/ruby/gems/1.9.1/gems/activerecord-3.0.0/lib/active_r&lt;/code&gt;
&lt;/pre&gt;
&lt;p&gt;ecord/connection_adapters/abstract/query_cache.rb:56:in
&lt;code&gt;select_all'&amp;lt;br/&amp;gt;&lt;/code&gt;&lt;/p&gt;
&lt;pre&gt;
&lt;code&gt;    from C:/Ruby192/lib/ruby/gems/1.9.1/gems/activerecord-3.0.0/lib/active_r&lt;/code&gt;
&lt;/pre&gt;
&lt;p&gt;ecord/connection_adapters/abstract/database_statements.rb:13:in
&lt;code&gt;select_one'&amp;lt;br/&amp;gt;&lt;/code&gt;&lt;/p&gt;
&lt;pre&gt;
&lt;code&gt;    from C:/Ruby192/lib/ruby/gems/1.9.1/gems/activerecord-3.0.0/lib/active_r&lt;/code&gt;
&lt;/pre&gt;
&lt;p&gt;ecord/connection_adapters/abstract/database_statements.rb:19:in
&lt;code&gt;select_value'&amp;lt;br/&amp;gt;&lt;/code&gt;&lt;/p&gt;
&lt;pre&gt;
&lt;code&gt;    from C:/Ruby192/lib/ruby/gems/1.9.1/gems/activerecord-3.0.0/lib/active_r&lt;/code&gt;
&lt;/pre&gt;
&lt;p&gt;ecord/relation/calculations.rb:196:in
&lt;code&gt;execute_simple_calculation'&amp;lt;br/&amp;gt;&lt;/code&gt;&lt;/p&gt;
&lt;pre&gt;
&lt;code&gt;    from C:/Ruby192/lib/ruby/gems/1.9.1/gems/activerecord-3.0.0/lib/active_r&lt;/code&gt;
&lt;/pre&gt;
&lt;p&gt;ecord/relation/calculations.rb:183:in
&lt;code&gt;perform_calculation'&amp;lt;br/&amp;gt;&lt;/code&gt;&lt;/p&gt;
&lt;pre&gt;
&lt;code&gt;    from C:/Ruby192/lib/ruby/gems/1.9.1/gems/activerecord-3.0.0/lib/active_r&lt;/code&gt;
&lt;/pre&gt;
&lt;p&gt;ecord/relation/calculations.rb:152:in
&lt;code&gt;calculate'&amp;lt;br/&amp;gt;&lt;/code&gt;&lt;/p&gt;
&lt;pre&gt;
&lt;code&gt;    from C:/Ruby192/lib/ruby/gems/1.9.1/gems/activerecord-3.0.0/lib/active_r&lt;/code&gt;
&lt;/pre&gt;
&lt;p&gt;ecord/relation/calculations.rb:58:in
&lt;code&gt;count'&amp;lt;br/&amp;gt;&lt;/code&gt;&lt;/p&gt;
&lt;pre&gt;
&lt;code&gt;    from C:in `count'
    from D:/vob/g2/config/initializers/cargo_category_load.rb:95:in `&amp;lt;top (r&lt;/code&gt;
&lt;/pre&gt;
&lt;p&gt;equired)&amp;gt;'&lt;br&gt;&lt;/p&gt;
&lt;pre&gt;
&lt;code&gt;    from C:/Ruby192/lib/ruby/gems/1.9.1/gems/activesupport-3.0.0/lib/active_&lt;/code&gt;
&lt;/pre&gt;
&lt;p&gt;support/dependencies.rb:235:in &lt;code&gt;load'&amp;lt;br/&amp;gt;&lt;/code&gt;&lt;/p&gt;
&lt;pre&gt;
&lt;code&gt;    from C:/Ruby192/lib/ruby/gems/1.9.1/gems/activesupport-3.0.0/lib/active_&lt;/code&gt;
&lt;/pre&gt;
&lt;p&gt;support/dependencies.rb:235:in &lt;code&gt;block in
load'&amp;lt;br/&amp;gt;&lt;/code&gt;&lt;/p&gt;
&lt;pre&gt;
&lt;code&gt;    from C:/Ruby192/lib/ruby/gems/1.9.1/gems/activesupport-3.0.0/lib/active_&lt;/code&gt;
&lt;/pre&gt;
&lt;p&gt;support/dependencies.rb:225:in &lt;code&gt;block in
load_dependency'&amp;lt;br/&amp;gt;&lt;/code&gt;&lt;/p&gt;
&lt;pre&gt;
&lt;code&gt;    from C:/Ruby192/lib/ruby/gems/1.9.1/gems/activesupport-3.0.0/lib/active_&lt;/code&gt;
&lt;/pre&gt;
&lt;p&gt;support/dependencies.rb:591:in
&lt;code&gt;new_constants_in'&amp;lt;br/&amp;gt;&lt;/code&gt;&lt;/p&gt;
&lt;pre&gt;
&lt;code&gt;    from C:/Ruby192/lib/ruby/gems/1.9.1/gems/activesupport-3.0.0/lib/active_&lt;/code&gt;
&lt;/pre&gt;
&lt;p&gt;support/dependencies.rb:225:in
&lt;code&gt;load_dependency'&amp;lt;br/&amp;gt;&lt;/code&gt;&lt;/p&gt;
&lt;pre&gt;
&lt;code&gt;    from C:/Ruby192/lib/ruby/gems/1.9.1/gems/activesupport-3.0.0/lib/active_&lt;/code&gt;
&lt;/pre&gt;
&lt;p&gt;support/dependencies.rb:235:in &lt;code&gt;load'&amp;lt;br/&amp;gt;&lt;/code&gt;&lt;/p&gt;
&lt;pre&gt;
&lt;code&gt;    from C:/Ruby192/lib/ruby/gems/1.9.1/gems/railties-3.0.0/lib/rails/engine&lt;/code&gt;
&lt;/pre&gt;
&lt;p&gt;.rb:201:in &lt;code&gt;block (2 levels) in
&amp;lt;class:Engine&amp;gt;'&lt;/code&gt;&lt;/p&gt;
&lt;pre&gt;
&lt;code&gt;    from C:/Ruby192/lib/ruby/gems/1.9.1/gems/railties-3.0.0/lib/rails/engine&lt;/code&gt;
&lt;/pre&gt;
&lt;p&gt;.rb:200:in &lt;code&gt;each'&lt;/code&gt;&lt;/p&gt;
&lt;pre&gt;
&lt;code&gt;    from C:/Ruby192/lib/ruby/gems/1.9.1/gems/railties-3.0.0/lib/rails/engine&lt;/code&gt;
&lt;/pre&gt;
&lt;p&gt;.rb:200:in &lt;code&gt;block in &amp;lt;class:Engine&amp;gt;'&lt;/code&gt;&lt;/p&gt;
&lt;pre&gt;
&lt;code&gt;    from C:/Ruby192/lib/ruby/gems/1.9.1/gems/railties-3.0.0/lib/rails/initia&lt;/code&gt;
&lt;/pre&gt;
&lt;p&gt;lizable.rb:25:in &lt;code&gt;instance_exec'&amp;lt;br/&amp;gt;&lt;/code&gt;&lt;/p&gt;
&lt;pre&gt;
&lt;code&gt;    from C:/Ruby192/lib/ruby/gems/1.9.1/gems/railties-3.0.0/lib/rails/initia&lt;/code&gt;
&lt;/pre&gt;
&lt;p&gt;lizable.rb:25:in &lt;code&gt;run'&amp;lt;br/&amp;gt;&lt;/code&gt;&lt;/p&gt;
&lt;pre&gt;
&lt;code&gt;    from C:/Ruby192/lib/ruby/gems/1.9.1/gems/railties-3.0.0/lib/rails/initia&lt;/code&gt;
&lt;/pre&gt;
&lt;p&gt;lizable.rb:50:in &lt;code&gt;block in
run_initializers'&amp;lt;br/&amp;gt;&lt;/code&gt;&lt;/p&gt;
&lt;pre&gt;
&lt;code&gt;    from C:/Ruby192/lib/ruby/gems/1.9.1/gems/railties-3.0.0/lib/rails/initia&lt;/code&gt;
&lt;/pre&gt;
&lt;p&gt;lizable.rb:49:in &lt;code&gt;each'&amp;lt;br/&amp;gt;&lt;/code&gt;&lt;/p&gt;
&lt;pre&gt;
&lt;code&gt;    from C:/Ruby192/lib/ruby/gems/1.9.1/gems/railties-3.0.0/lib/rails/initia&lt;/code&gt;
&lt;/pre&gt;
&lt;p&gt;lizable.rb:49:in &lt;code&gt;run_initializers'&amp;lt;br/&amp;gt;&lt;/code&gt;&lt;/p&gt;
&lt;pre&gt;
&lt;code&gt;    from C:/Ruby192/lib/ruby/gems/1.9.1/gems/railties-3.0.0/lib/rails/applic&lt;/code&gt;
&lt;/pre&gt;
&lt;p&gt;ation.rb:134:in &lt;code&gt;initialize!'&amp;lt;br/&amp;gt;&lt;/code&gt;&lt;/p&gt;
&lt;pre&gt;
&lt;code&gt;    from C:/Ruby192/lib/ruby/gems/1.9.1/gems/railties-3.0.0/lib/rails/applic&lt;/code&gt;
&lt;/pre&gt;
&lt;p&gt;ation.rb:77:in &lt;code&gt;method_missing'&amp;lt;br/&amp;gt;&lt;/code&gt;&lt;/p&gt;
&lt;pre&gt;
&lt;code&gt;    from D:/vob/g2/config/environment.rb:5:in `&amp;lt;top (required)&amp;gt;'
    from D:/vob/g2/config.ru:3:in `require'
    from D:/vob/g2/config.ru:3:in `block in &amp;lt;main&amp;gt;'
    from C:/Ruby192/lib/ruby/gems/1.9.1/gems/rack-1.2.1/lib/rack/builder.rb:&lt;/code&gt;
&lt;/pre&gt;
&lt;p&gt;46:in &lt;code&gt;instance_eval'&amp;lt;br/&amp;gt;&lt;/code&gt;&lt;/p&gt;
&lt;pre&gt;
&lt;code&gt;    from C:/Ruby192/lib/ruby/gems/1.9.1/gems/rack-1.2.1/lib/rack/builder.rb:&lt;/code&gt;
&lt;/pre&gt;
&lt;p&gt;46:in &lt;code&gt;initialize'&amp;lt;br/&amp;gt;&lt;/code&gt;&lt;/p&gt;
&lt;pre&gt;
&lt;code&gt;    from D:/vob/g2/config.ru:1:in `new'
    from D:/vob/g2/config.ru:1:in `&amp;lt;main&amp;gt;'
    from C:/Ruby192/lib/ruby/gems/1.9.1/gems/rack-1.2.1/lib/rack/builder.rb:&lt;/code&gt;
&lt;/pre&gt;
&lt;p&gt;35:in &lt;code&gt;eval'&amp;lt;br/&amp;gt;&lt;/code&gt;&lt;/p&gt;
&lt;pre&gt;
&lt;code&gt;    from C:/Ruby192/lib/ruby/gems/1.9.1/gems/rack-1.2.1/lib/rack/builder.rb:&lt;/code&gt;
&lt;/pre&gt;
&lt;p&gt;35:in &lt;code&gt;parse_file'&amp;lt;br/&amp;gt;&lt;/code&gt;&lt;/p&gt;
&lt;pre&gt;
&lt;code&gt;    from C:/Ruby192/lib/ruby/gems/1.9.1/gems/rack-1.2.1/lib/rack/server.rb:1&lt;/code&gt;
&lt;/pre&gt;
&lt;p&gt;62:in &lt;code&gt;app'&amp;lt;br/&amp;gt;&lt;/code&gt;&lt;/p&gt;
&lt;pre&gt;
&lt;code&gt;    from C:/Ruby192/lib/ruby/gems/1.9.1/gems/rack-1.2.1/lib/rack/server.rb:2&lt;/code&gt;
&lt;/pre&gt;
&lt;p&gt;48:in &lt;code&gt;wrapped_app'&amp;lt;br/&amp;gt;&lt;/code&gt;&lt;/p&gt;
&lt;pre&gt;
&lt;code&gt;    from C:/Ruby192/lib/ruby/gems/1.9.1/gems/rack-1.2.1/lib/rack/server.rb:2&lt;/code&gt;
&lt;/pre&gt;
&lt;p&gt;13:in &lt;code&gt;start'&amp;lt;br/&amp;gt;&lt;/code&gt;&lt;/p&gt;
&lt;pre&gt;
&lt;code&gt;    from C:/Ruby192/lib/ruby/gems/1.9.1/gems/railties-3.0.0/lib/rails/comman&lt;/code&gt;
&lt;/pre&gt;
&lt;p&gt;ds/server.rb:65:in &lt;code&gt;start'&amp;lt;br/&amp;gt;&lt;/code&gt;&lt;/p&gt;
&lt;pre&gt;
&lt;code&gt;    from C:/Ruby192/lib/ruby/gems/1.9.1/gems/railties-3.0.0/lib/rails/comman&lt;/code&gt;
&lt;/pre&gt;
&lt;p&gt;ds.rb:30:in &lt;code&gt;block in &amp;lt;top
(required)&amp;gt;'&amp;lt;br/&amp;gt;&lt;/code&gt;&lt;/p&gt;
&lt;pre&gt;
&lt;code&gt;    from C:/Ruby192/lib/ruby/gems/1.9.1/gems/railties-3.0.0/lib/rails/comman&lt;/code&gt;
&lt;/pre&gt;
&lt;p&gt;ds.rb:27:in &lt;code&gt;tap'&amp;lt;br/&amp;gt;&lt;/code&gt;&lt;/p&gt;
&lt;pre&gt;
&lt;code&gt;    from C:/Ruby192/lib/ruby/gems/1.9.1/gems/railties-3.0.0/lib/rails/comman&lt;/code&gt;
&lt;/pre&gt;
&lt;p&gt;ds.rb:27:in &lt;code&gt;&amp;lt;top (required)&amp;gt;'&amp;lt;br/&amp;gt;&lt;/code&gt;&lt;/p&gt;
&lt;pre&gt;
&lt;code&gt;    from script/rails:6:in `require'
    from script/rails:6:in `&amp;lt;main&amp;gt;'&lt;/code&gt;
&lt;/pre&gt;&lt;/div&gt;</body-html>
      <closed type="boolean">false</closed>
      <created-at type="datetime">2010-09-03T16:06:18+01:00</created-at>
      <creator-id type="integer">91469</creator-id>
      <diffable-attributes type="yaml">--- {}

</diffable-attributes>
      <milestone-id type="integer" nil="true"></milestone-id>
      <number type="integer">5549</number>
      <permalink>activerecordcalculationscount-not-work-when-mysql-table-is-empty</permalink>
      <priority type="integer">0</priority>
      <project-id type="integer">8994</project-id>
      <state>new</state>
      <tag>&quot;activerecord  calculation&quot;</tag>
      <title>ActiveRecord::Calculations.count( )  not work , when mysql table is empty</title>
      <updated-at type="datetime">2010-09-03T16:06:20+01:00</updated-at>
      <user-id type="integer">91469</user-id>
      <version type="integer">1</version>
      <user-name>Hunter</user-name>
      <creator-name>Hunter</creator-name>
      <url>http://rails.lighthouseapp.com/projects/8994/tickets/5549</url>
      <priority-name nil="true"></priority-name>
    </version>
    <version type="Ticket::Version">
      <assigned-user-id type="integer" nil="true"></assigned-user-id>
      <attachments-count type="integer">0</attachments-count>
      <body>Can you post the query that is breaking?</body>
      <body-html>&lt;div&gt;&lt;p&gt;Can you post the query that is breaking?&lt;/p&gt;&lt;/div&gt;</body-html>
      <closed type="boolean">false</closed>
      <created-at type="datetime">2010-09-03T18:38:02+01:00</created-at>
      <creator-id type="integer">91469</creator-id>
      <diffable-attributes type="yaml">--- 
:priority: 0
</diffable-attributes>
      <milestone-id type="integer" nil="true"></milestone-id>
      <number type="integer">5549</number>
      <permalink>activerecordcalculationscount-not-work-when-mysql-table-is-empty</permalink>
      <priority type="integer">3</priority>
      <project-id type="integer">8994</project-id>
      <state>new</state>
      <tag>&quot;activerecord  calculation&quot;</tag>
      <title>ActiveRecord::Calculations.count( )  not work , when mysql table is empty</title>
      <updated-at type="datetime">2010-09-03T18:38:12+01:00</updated-at>
      <user-id type="integer">40263</user-id>
      <version type="integer">2</version>
      <user-name>Neeraj Singh</user-name>
      <creator-name>Hunter</creator-name>
      <url>http://rails.lighthouseapp.com/projects/8994/tickets/5549</url>
      <priority-name>Low</priority-name>
    </version>
    <version type="Ticket::Version">
      <assigned-user-id type="integer" nil="true"></assigned-user-id>
      <attachments-count type="integer">0</attachments-count>
      <body>the trace stack is already in the post.

extract the excetion for count here:

from C:/Ruby192/lib/ruby/gems/1.9.1/gems/activerecord-3.0.0/lib/active_r
ecord/relation/calculations.rb:58:in count'&lt;br/&gt;

    from C:in `count'
    from D:/vob/g2/config/initializers/cargo_category_load.rb:95:in `&lt;top (r
equired)&gt;'



mysql_adapter.rb:629:in select': undefined methodall_hashes' for
#&lt;Mysql::Result:0x19b94c8&gt; (NoMethodError)

, and not only for count , but also for other method, like all, will get same break.</body>
      <body-html>&lt;div&gt;&lt;p&gt;the trace stack is already in the post.&lt;/p&gt;
&lt;p&gt;extract the excetion for count here:&lt;/p&gt;
&lt;p&gt;from
C:/Ruby192/lib/ruby/gems/1.9.1/gems/activerecord-3.0.0/lib/active_r&lt;br&gt;
ecord/relation/calculations.rb:58:in count'&lt;br&gt;&lt;/p&gt;
&lt;pre&gt;
&lt;code&gt;from C:in `count'
from D:/vob/g2/config/initializers/cargo_category_load.rb:95:in `&amp;lt;top (r&lt;/code&gt;
&lt;/pre&gt;
&lt;p&gt;equired)&amp;gt;'&lt;/p&gt;
&lt;p&gt;mysql_adapter.rb:629:in select': undefined methodall_hashes'
for&lt;br&gt;&lt;/p&gt;
&lt;h1&gt;&amp;lt;Mysql::Result:0x19b94c8&amp;gt; (NoMethodError)&lt;/h1&gt;
&lt;p&gt;, and not only for count , but also for other method, like all,
will get same break.&lt;/p&gt;&lt;/div&gt;</body-html>
      <closed type="boolean">false</closed>
      <created-at type="datetime">2010-09-04T02:59:16+01:00</created-at>
      <creator-id type="integer">91469</creator-id>
      <diffable-attributes type="yaml">--- {}

</diffable-attributes>
      <milestone-id type="integer" nil="true"></milestone-id>
      <number type="integer">5549</number>
      <permalink>activerecordcalculationscount-not-work-when-mysql-table-is-empty</permalink>
      <priority type="integer">3</priority>
      <project-id type="integer">8994</project-id>
      <state>new</state>
      <tag>&quot;activerecord  calculation&quot;</tag>
      <title>ActiveRecord::Calculations.count( )  not work , when mysql table is empty</title>
      <updated-at type="datetime">2010-09-04T02:59:19+01:00</updated-at>
      <user-id type="integer">91469</user-id>
      <version type="integer">3</version>
      <user-name>Hunter</user-name>
      <creator-name>Hunter</creator-name>
      <url>http://rails.lighthouseapp.com/projects/8994/tickets/5549</url>
      <priority-name>Low</priority-name>
    </version>
    <version type="Ticket::Version">
      <assigned-user-id type="integer" nil="true"></assigned-user-id>
      <attachments-count type="integer">0</attachments-count>
      <body>I was unable to reproduce this on edge Rails using Ruby 1.9.2:

@@@

&#10140;  in ~/code/rails/railties/tmp on 5549 (&#10004;) using ruby-1.9.2-p0@edgerailsapp ../../bin/rails new ticket_5549 --dev -d mysql
...
&#10140;  in ~/code/rails/railties/tmp on 5549 (&#10004;) using ruby-1.9.2-p0@edgerailsapp cd ticket_5549 
&#10140;  in ~/code/rails/railties/tmp/ticket_5549 on 5549 (&#10004;) using ruby-1.9.2-p0@edgerailsapp bundle exec rails g model foo
...
&#10140;  in ~/code/rails/railties/tmp/ticket_5549 on 5549 (&#10004;) using ruby-1.9.2-p0@edgerailsapp rake db:create
(in /Users/dtrasbo/code/rails/railties/tmp/ticket_5549)
&#10140;  in ~/code/rails/railties/tmp/ticket_5549 on 5549 (&#10004;) using ruby-1.9.2-p0@edgerailsapp rake db:migrate
(in /Users/dtrasbo/code/rails/railties/tmp/ticket_5549)
..
&#10140;  in ~/code/rails/railties/tmp/ticket_5549 on 5549 (&#10004;) using ruby-1.9.2-p0@edgerailsapp cat config/database.yml 
# MySQL.  Versions 4.1 and 5.0 are recommended.
#
# Install the MySQL driver:
#   gem install mysql2
#
# And be sure to use new-style password hashing:
#   http://dev.mysql.com/doc/refman/5.0/en/old-client.html
development:
  adapter: mysql2
  encoding: utf8
  reconnect: false
  database: ticket_5549_development
  pool: 5
  username: root
  password:
  socket: /tmp/mysql.sock

test:
...
&#10140;  in ~/code/rails/railties/tmp/ticket_5549 on 5549 (&#10004;) using ruby-1.9.2-p0@edgerailsapp bundle exec rails c 
Loading development environment (Rails 3.1.0.beta)
ruby-1.9.2-p0 &gt; Foo.count
 =&gt; 0 
ruby-1.9.2-p0 &gt; exit
&#10140;  in ~/code/rails/railties/tmp/ticket_5549 on 5549 (&#10004;) using ruby-1.9.2-p0@edgerailsapp mysql --version
mysql  Ver 14.14 Distrib 5.1.49, for apple-darwin10.4.0 (i386) using readline 6.0
@@@

I'm on OS X.</body>
      <body-html>&lt;div&gt;&lt;p&gt;I was unable to reproduce this on edge Rails using Ruby
1.9.2:&lt;/p&gt;
&lt;pre&gt;
&lt;code&gt;
&amp;#10140;  in ~/code/rails/railties/tmp on 5549 (&amp;#10004;) using ruby-1.9.2-p0@edgerailsapp ../../bin/rails new ticket_5549 --dev -d mysql
...
&amp;#10140;  in ~/code/rails/railties/tmp on 5549 (&amp;#10004;) using ruby-1.9.2-p0@edgerailsapp cd ticket_5549 
&amp;#10140;  in ~/code/rails/railties/tmp/ticket_5549 on 5549 (&amp;#10004;) using ruby-1.9.2-p0@edgerailsapp bundle exec rails g model foo
...
&amp;#10140;  in ~/code/rails/railties/tmp/ticket_5549 on 5549 (&amp;#10004;) using ruby-1.9.2-p0@edgerailsapp rake db:create
(in /Users/dtrasbo/code/rails/railties/tmp/ticket_5549)
&amp;#10140;  in ~/code/rails/railties/tmp/ticket_5549 on 5549 (&amp;#10004;) using ruby-1.9.2-p0@edgerailsapp rake db:migrate
(in /Users/dtrasbo/code/rails/railties/tmp/ticket_5549)
..
&amp;#10140;  in ~/code/rails/railties/tmp/ticket_5549 on 5549 (&amp;#10004;) using ruby-1.9.2-p0@edgerailsapp cat config/database.yml 
# MySQL.  Versions 4.1 and 5.0 are recommended.
#
# Install the MySQL driver:
#   gem install mysql2
#
# And be sure to use new-style password hashing:
#   http://dev.mysql.com/doc/refman/5.0/en/old-client.html
development:
  adapter: mysql2
  encoding: utf8
  reconnect: false
  database: ticket_5549_development
  pool: 5
  username: root
  password:
  socket: /tmp/mysql.sock

test:
...
&amp;#10140;  in ~/code/rails/railties/tmp/ticket_5549 on 5549 (&amp;#10004;) using ruby-1.9.2-p0@edgerailsapp bundle exec rails c 
Loading development environment (Rails 3.1.0.beta)
ruby-1.9.2-p0 &amp;gt; Foo.count
 =&amp;gt; 0 
ruby-1.9.2-p0 &amp;gt; exit
&amp;#10140;  in ~/code/rails/railties/tmp/ticket_5549 on 5549 (&amp;#10004;) using ruby-1.9.2-p0@edgerailsapp mysql --version
mysql  Ver 14.14 Distrib 5.1.49, for apple-darwin10.4.0 (i386) using readline 6.0&lt;/code&gt;
&lt;/pre&gt;
&lt;p&gt;I'm on OS X.&lt;/p&gt;&lt;/div&gt;</body-html>
      <closed type="boolean">false</closed>
      <created-at type="datetime">2010-09-05T18:31:20+01:00</created-at>
      <creator-id type="integer">91469</creator-id>
      <diffable-attributes type="yaml">--- {}

</diffable-attributes>
      <milestone-id type="integer" nil="true"></milestone-id>
      <number type="integer">5549</number>
      <permalink>activerecordcalculationscount-not-work-when-mysql-table-is-empty</permalink>
      <priority type="integer">3</priority>
      <project-id type="integer">8994</project-id>
      <state>new</state>
      <tag>&quot;activerecord  calculation&quot;</tag>
      <title>ActiveRecord::Calculations.count( )  not work , when mysql table is empty</title>
      <updated-at type="datetime">2010-09-05T18:31:25+01:00</updated-at>
      <user-id type="integer">65050</user-id>
      <version type="integer">4</version>
      <user-name>David Trasbo</user-name>
      <creator-name>Hunter</creator-name>
      <url>http://rails.lighthouseapp.com/projects/8994/tickets/5549</url>
      <priority-name>Low</priority-name>
    </version>
    <version type="Ticket::Version">
      <assigned-user-id type="integer" nil="true"></assigned-user-id>
      <attachments-count type="integer">0</attachments-count>
      <body>That turned out to be a bit crufty. Here we go again:

@@@
&#10140; ../../bin/rails new ticket_5549 --dev -d mysql...
&#10140; cd ticket_5549 &#10140; bundle exec rails g model foo...
&#10140; rake db:create(in /Users/dtrasbo/code/rails/railties/tmp/ticket_5549)
&#10140; rake db:migrate(in /Users/dtrasbo/code/rails/railties/tmp/ticket_5549)
..
&#10140; cat config/database.yml # MySQL.  Versions 4.1 and 5.0 are recommended.
#
# Install the MySQL driver:
#   gem install mysql2
#
# And be sure to use new-style password hashing:
#   http://dev.mysql.com/doc/refman/5.0/en/old-client.html
development:
  adapter: mysql2
  encoding: utf8
  reconnect: false
  database: ticket_5549_development
  pool: 5
  username: root
  password:
  socket: /tmp/mysql.sock

test:
...
&#10140; bundle exec rails c Loading development environment (Rails 3.1.0.beta)
ruby-1.9.2-p0 &gt; Foo.count
 =&gt; 0 
ruby-1.9.2-p0 &gt; exit
&#10140; mysql --versionmysql  Ver 14.14 Distrib 5.1.49, for apple-darwin10.4.0 (i386) using readline 6.0
@@@</body>
      <body-html>&lt;div&gt;&lt;p&gt;That turned out to be a bit crufty. Here we go again:&lt;/p&gt;
&lt;pre&gt;
&lt;code&gt;&amp;#10140; ../../bin/rails new ticket_5549 --dev -d mysql...
&amp;#10140; cd ticket_5549 &amp;#10140; bundle exec rails g model foo...
&amp;#10140; rake db:create(in /Users/dtrasbo/code/rails/railties/tmp/ticket_5549)
&amp;#10140; rake db:migrate(in /Users/dtrasbo/code/rails/railties/tmp/ticket_5549)
..
&amp;#10140; cat config/database.yml # MySQL.  Versions 4.1 and 5.0 are recommended.
#
# Install the MySQL driver:
#   gem install mysql2
#
# And be sure to use new-style password hashing:
#   http://dev.mysql.com/doc/refman/5.0/en/old-client.html
development:
  adapter: mysql2
  encoding: utf8
  reconnect: false
  database: ticket_5549_development
  pool: 5
  username: root
  password:
  socket: /tmp/mysql.sock

test:
...
&amp;#10140; bundle exec rails c Loading development environment (Rails 3.1.0.beta)
ruby-1.9.2-p0 &amp;gt; Foo.count
 =&amp;gt; 0 
ruby-1.9.2-p0 &amp;gt; exit
&amp;#10140; mysql --versionmysql  Ver 14.14 Distrib 5.1.49, for apple-darwin10.4.0 (i386) using readline 6.0&lt;/code&gt;
&lt;/pre&gt;&lt;/div&gt;</body-html>
      <closed type="boolean">false</closed>
      <created-at type="datetime">2010-09-05T18:36:38+01:00</created-at>
      <creator-id type="integer">91469</creator-id>
      <diffable-attributes type="yaml">--- {}

</diffable-attributes>
      <milestone-id type="integer" nil="true"></milestone-id>
      <number type="integer">5549</number>
      <permalink>activerecordcalculationscount-not-work-when-mysql-table-is-empty</permalink>
      <priority type="integer">3</priority>
      <project-id type="integer">8994</project-id>
      <state>new</state>
      <tag>&quot;activerecord  calculation&quot;</tag>
      <title>ActiveRecord::Calculations.count( )  not work , when mysql table is empty</title>
      <updated-at type="datetime">2010-09-05T18:36:39+01:00</updated-at>
      <user-id type="integer">65050</user-id>
      <version type="integer">5</version>
      <user-name>David Trasbo</user-name>
      <creator-name>Hunter</creator-name>
      <url>http://rails.lighthouseapp.com/projects/8994/tickets/5549</url>
      <priority-name>Low</priority-name>
    </version>
    <version type="Ticket::Version">
      <assigned-user-id type="integer" nil="true"></assigned-user-id>
      <attachments-count type="integer">0</attachments-count>
      <body>Hi, Thanks for your quick action on this fault.

Something clarify here.

1. I use mysql gem rather than mysql2

2. I am on windows platform

3. when I switch back to Rails 2.3.5, everything ok, and no exception .


Brs

Hunter Hu</body>
      <body-html>&lt;div&gt;&lt;p&gt;Hi, Thanks for your quick action on this fault.&lt;/p&gt;
&lt;p&gt;Something clarify here.&lt;/p&gt;
&lt;ol&gt;
&lt;li&gt;
&lt;p&gt;I use mysql gem rather than mysql2&lt;/p&gt;
&lt;/li&gt;
&lt;li&gt;
&lt;p&gt;I am on windows platform&lt;/p&gt;
&lt;/li&gt;
&lt;li&gt;
&lt;p&gt;when I switch back to Rails 2.3.5, everything ok, and no
exception .&lt;/p&gt;
&lt;/li&gt;
&lt;/ol&gt;
&lt;p&gt;Brs&lt;/p&gt;
&lt;p&gt;Hunter Hu&lt;/p&gt;&lt;/div&gt;</body-html>
      <closed type="boolean">false</closed>
      <created-at type="datetime">2010-09-07T02:37:45+01:00</created-at>
      <creator-id type="integer">91469</creator-id>
      <diffable-attributes type="yaml">--- {}

</diffable-attributes>
      <milestone-id type="integer" nil="true"></milestone-id>
      <number type="integer">5549</number>
      <permalink>activerecordcalculationscount-not-work-when-mysql-table-is-empty</permalink>
      <priority type="integer">3</priority>
      <project-id type="integer">8994</project-id>
      <state>new</state>
      <tag>&quot;activerecord  calculation&quot;</tag>
      <title>ActiveRecord::Calculations.count( )  not work , when mysql table is empty</title>
      <updated-at type="datetime">2010-09-07T02:37:47+01:00</updated-at>
      <user-id type="integer">91469</user-id>
      <version type="integer">6</version>
      <user-name>Hunter</user-name>
      <creator-name>Hunter</creator-name>
      <url>http://rails.lighthouseapp.com/projects/8994/tickets/5549</url>
      <priority-name>Low</priority-name>
    </version>
    <version type="Ticket::Version">
      <assigned-user-id type="integer" nil="true"></assigned-user-id>
      <attachments-count type="integer">0</attachments-count>
      <body>Ah, okay. I repeated the process above except I used the `mysql` adapter/gem instead but I still couldn't reproduce. That leaves Windows.

I do have access to a Windows machine with Ruby but I won't be near it before tomorrow. I'll try and see if I can reproduce this then.</body>
      <body-html>&lt;div&gt;&lt;p&gt;Ah, okay. I repeated the process above except I used the
&lt;code&gt;mysql&lt;/code&gt; adapter/gem instead but I still couldn't
reproduce. That leaves Windows.&lt;/p&gt;
&lt;p&gt;I do have access to a Windows machine with Ruby but I won't be
near it before tomorrow. I'll try and see if I can reproduce this
then.&lt;/p&gt;&lt;/div&gt;</body-html>
      <closed type="boolean">false</closed>
      <created-at type="datetime">2010-09-07T12:25:36+01:00</created-at>
      <creator-id type="integer">91469</creator-id>
      <diffable-attributes type="yaml">--- {}

</diffable-attributes>
      <milestone-id type="integer" nil="true"></milestone-id>
      <number type="integer">5549</number>
      <permalink>activerecordcalculationscount-not-work-when-mysql-table-is-empty</permalink>
      <priority type="integer">3</priority>
      <project-id type="integer">8994</project-id>
      <state>new</state>
      <tag>&quot;activerecord  calculation&quot;</tag>
      <title>ActiveRecord::Calculations.count( )  not work , when mysql table is empty</title>
      <updated-at type="datetime">2010-09-07T12:25:39+01:00</updated-at>
      <user-id type="integer">65050</user-id>
      <version type="integer">7</version>
      <user-name>David Trasbo</user-name>
      <creator-name>Hunter</creator-name>
      <url>http://rails.lighthouseapp.com/projects/8994/tickets/5549</url>
      <priority-name>Low</priority-name>
    </version>
    <version type="Ticket::Version">
      <assigned-user-id type="integer" nil="true"></assigned-user-id>
      <attachments-count type="integer">0</attachments-count>
      <body>This issue has been automatically marked as stale because it has not been commented on for at least three months.

The resources of the Rails core team are limited, and so we are asking for your help. If you can still reproduce this error on the 3-0-stable branch or on master, please reply with all of the information you have about it and add &quot;[state:open]&quot; to your comment. This will reopen the ticket for review. Likewise, if you feel that this is a very important feature for Rails to include, please reply with your explanation so we can consider it.

Thank you for all your contributions, and we hope you will understand this step to focus our efforts where they are most helpful.</body>
      <body-html>&lt;div&gt;&lt;p&gt;This issue has been automatically marked as stale because it has
not been commented on for at least three months.&lt;/p&gt;
&lt;p&gt;The resources of the Rails core team are limited, and so we are
asking for your help. If you can still reproduce this error on the
3-0-stable branch or on master, please reply with all of the
information you have about it and add &quot;[state:open]&quot; to your
comment. This will reopen the ticket for review. Likewise, if you
feel that this is a very important feature for Rails to include,
please reply with your explanation so we can consider it.&lt;/p&gt;
&lt;p&gt;Thank you for all your contributions, and we hope you will
understand this step to focus our efforts where they are most
helpful.&lt;/p&gt;&lt;/div&gt;</body-html>
      <closed type="boolean">false</closed>
      <created-at type="datetime">2011-02-02T16:32:21+00:00</created-at>
      <creator-id type="integer">91469</creator-id>
      <diffable-attributes type="yaml">--- 
:state: new
</diffable-attributes>
      <milestone-id type="integer" nil="true"></milestone-id>
      <number type="integer">5549</number>
      <permalink>activerecordcalculationscount-not-work-when-mysql-table-is-empty</permalink>
      <priority type="integer">3</priority>
      <project-id type="integer">8994</project-id>
      <state>open</state>
      <tag>&quot;activerecord  calculation&quot;</tag>
      <title>ActiveRecord::Calculations.count( )  not work , when mysql table is empty</title>
      <updated-at type="datetime">2011-02-02T16:53:19+00:00</updated-at>
      <user-id type="integer">40272</user-id>
      <version type="integer">8</version>
      <user-name>Santiago Pastorino</user-name>
      <creator-name>Hunter</creator-name>
      <url>http://rails.lighthouseapp.com/projects/8994/tickets/5549</url>
      <priority-name>Low</priority-name>
    </version>
    <version type="Ticket::Version">
      <assigned-user-id type="integer" nil="true"></assigned-user-id>
      <attachments-count type="integer">0</attachments-count>
      <body nil="true"></body>
      <body-html nil="true"></body-html>
      <closed type="boolean">true</closed>
      <created-at type="datetime">2011-02-02T16:32:23+00:00</created-at>
      <creator-id type="integer">91469</creator-id>
      <diffable-attributes type="yaml">--- 
:state: open
</diffable-attributes>
      <milestone-id type="integer" nil="true"></milestone-id>
      <number type="integer">5549</number>
      <permalink>activerecordcalculationscount-not-work-when-mysql-table-is-empty</permalink>
      <priority type="integer">3</priority>
      <project-id type="integer">8994</project-id>
      <state>stale</state>
      <tag>&quot;activerecord  calculation&quot;</tag>
      <title>ActiveRecord::Calculations.count( )  not work , when mysql table is empty</title>
      <updated-at type="datetime">2011-02-02T16:53:31+00:00</updated-at>
      <user-id type="integer">40272</user-id>
      <version type="integer">9</version>
      <user-name>Santiago Pastorino</user-name>
      <creator-name>Hunter</creator-name>
      <url>http://rails.lighthouseapp.com/projects/8994/tickets/5549</url>
      <priority-name>Low</priority-name>
    </version>
  </versions>
</ticket>
